<stg><name>getParallelograms</name>


<trans_list>

<trans id="143" from="1" to="2">
<condition id="-1">
<or_exp><and_exp></and_exp></or_exp>
</condition>
</trans>

<trans id="144" from="2" to="3">
<condition id="-1">
<or_exp><and_exp></and_exp></or_exp>
</condition>
</trans>

<trans id="145" from="3" to="4">
<condition id="-1">
<or_exp><and_exp></and_exp></or_exp>
</condition>
</trans>

<trans id="146" from="4" to="5">
<condition id="-1">
<or_exp><and_exp><literal name="icmp_ln59" val="0"/>
</and_exp></or_exp>
</condition>
</trans>

<trans id="148" from="5" to="6">
<condition id="-1">
<or_exp><and_exp></and_exp></or_exp>
</condition>
</trans>

<trans id="149" from="6" to="7">
<condition id="-1">
<or_exp><and_exp></and_exp></or_exp>
</condition>
</trans>

<trans id="150" from="7" to="8">
<condition id="-1">
<or_exp><and_exp></and_exp></or_exp>
</condition>
</trans>

<trans id="151" from="8" to="9">
<condition id="-1">
<or_exp><and_exp></and_exp></or_exp>
</condition>
</trans>

<trans id="152" from="9" to="10">
<condition id="-1">
<or_exp><and_exp></and_exp></or_exp>
</condition>
</trans>

<trans id="153" from="10" to="11">
<condition id="-1">
<or_exp><and_exp></and_exp></or_exp>
</condition>
</trans>

<trans id="154" from="11" to="12">
<condition id="-1">
<or_exp><and_exp></and_exp></or_exp>
</condition>
</trans>

<trans id="155" from="12" to="13">
<condition id="-1">
<or_exp><and_exp><literal name="icmp_ln70" val="1"/>
</and_exp></or_exp>
</condition>
</trans>

<trans id="156" from="12" to="16">
<condition id="-1">
<or_exp><and_exp><literal name="icmp_ln70" val="0"/>
</and_exp></or_exp>
</condition>
</trans>

<trans id="158" from="13" to="14">
<condition id="-1">
<or_exp><and_exp></and_exp></or_exp>
</condition>
</trans>

<trans id="159" from="14" to="15">
<condition id="-1">
<or_exp><and_exp></and_exp></or_exp>
</condition>
</trans>

<trans id="160" from="15" to="16">
<condition id="-1">
<or_exp><and_exp></and_exp></or_exp>
</condition>
</trans>

<trans id="161" from="16" to="4">
<condition id="-1">
<or_exp><and_exp></and_exp></or_exp>
</condition>
</trans>
</trans_list>



<state_list>

<state id="1" st_id="1">

<operation id="17" st_id="1" stage="1" lat="1">
<core>NULL</core>
<MemPortIdVec></MemPortIdVec>
<condition id="-1">
<or_exp><and_exp></and_exp></or_exp>
</condition>

<Node id="5" bw="32" op_0_bw="32">
<![CDATA[
:0 %empty = alloca i32 1

]]></Node>
<StgValue><ssdm name="empty"/></StgValue>
</operation>

<operation id="18" st_id="1" stage="1" lat="1">
<core>NULL</core>
<MemPortIdVec></MemPortIdVec>
<condition id="-1">
<or_exp><and_exp></and_exp></or_exp>
</condition>

<Node id="6" bw="8" op_0_bw="32" op_1_bw="64" op_2_bw="64">
<![CDATA[
:1 %wp_superpoints_addr = getelementptr i32 %wp_superpoints, i64 0, i64 1

]]></Node>
<StgValue><ssdm name="wp_superpoints_addr"/></StgValue>
</operation>

<operation id="19" st_id="1" stage="1" lat="1">
<core>NULL</core>
<MemPortIdVec></MemPortIdVec>
<condition id="-1">
<or_exp><and_exp></and_exp></or_exp>
</condition>

<Node id="7" bw="8" op_0_bw="32" op_1_bw="64" op_2_bw="64">
<![CDATA[
:2 %wp_superpoints_addr_2 = getelementptr i32 %wp_superpoints, i64 0, i64 31

]]></Node>
<StgValue><ssdm name="wp_superpoints_addr_2"/></StgValue>
</operation>

<operation id="20" st_id="1" stage="2" lat="2">
<core>RAM</core>
<MemPortIdVec>1 </MemPortIdVec>
<condition id="-1">
<or_exp><and_exp></and_exp></or_exp>
</condition>

<Node id="9" bw="32" op_0_bw="8">
<![CDATA[
:4 %wp_superpoints_load = load i8 %wp_superpoints_addr

]]></Node>
<StgValue><ssdm name="wp_superpoints_load"/></StgValue>
</operation>

<operation id="21" st_id="1" stage="2" lat="2">
<core>RAM</core>
<MemPortIdVec>0 </MemPortIdVec>
<condition id="-1">
<or_exp><and_exp></and_exp></or_exp>
</condition>

<Node id="13" bw="32" op_0_bw="8">
<![CDATA[
:8 %wp_superpoints_load_1 = load i8 %wp_superpoints_addr_2

]]></Node>
<StgValue><ssdm name="wp_superpoints_load_1"/></StgValue>
</operation>

<operation id="22" st_id="1" stage="1" lat="1">
<core>NULL</core>
<MemPortIdVec></MemPortIdVec>
<condition id="-1">
<or_exp><and_exp></and_exp></or_exp>
</condition>

<Node id="23" bw="0" op_0_bw="32" op_1_bw="32">
<![CDATA[
:18 %store_ln59 = store i32 0, i32 %empty

]]></Node>
<StgValue><ssdm name="store_ln59"/></StgValue>
</operation>
</state>

<state id="2" st_id="2">

<operation id="23" st_id="2" stage="1" lat="2">
<core>RAM</core>
<MemPortIdVec>1 </MemPortIdVec>
<condition id="-1">
<or_exp><and_exp></and_exp></or_exp>
</condition>

<Node id="9" bw="32" op_0_bw="8">
<![CDATA[
:4 %wp_superpoints_load = load i8 %wp_superpoints_addr

]]></Node>
<StgValue><ssdm name="wp_superpoints_load"/></StgValue>
</operation>

<operation id="24" st_id="2" stage="1" lat="1">
<core>Cmp</core>
<MemPortIdVec></MemPortIdVec>
<condition id="-1">
<or_exp><and_exp></and_exp></or_exp>
</condition>

<Node id="10" bw="1" op_0_bw="32" op_1_bw="32">
<![CDATA[
:5 %icmp_ln878 = icmp_slt  i32 %wp_superpoints_load, i32 4272967196

]]></Node>
<StgValue><ssdm name="icmp_ln878"/></StgValue>
</operation>

<operation id="25" st_id="2" stage="1" lat="2">
<core>RAM</core>
<MemPortIdVec>0 </MemPortIdVec>
<condition id="-1">
<or_exp><and_exp></and_exp></or_exp>
</condition>

<Node id="13" bw="32" op_0_bw="8">
<![CDATA[
:8 %wp_superpoints_load_1 = load i8 %wp_superpoints_addr_2

]]></Node>
<StgValue><ssdm name="wp_superpoints_load_1"/></StgValue>
</operation>

<operation id="26" st_id="2" stage="1" lat="1">
<core>Cmp</core>
<MemPortIdVec></MemPortIdVec>
<condition id="-1">
<or_exp><and_exp></and_exp></or_exp>
</condition>

<Node id="14" bw="1" op_0_bw="32" op_1_bw="32">
<![CDATA[
:9 %icmp_ln878_14 = icmp_slt  i32 %wp_superpoints_load_1, i32 22000100

]]></Node>
<StgValue><ssdm name="icmp_ln878_14"/></StgValue>
</operation>
</state>

<state id="3" st_id="3">

<operation id="27" st_id="3" stage="1" lat="1">
<core>NULL</core>
<MemPortIdVec></MemPortIdVec>
<condition id="-1">
<or_exp><and_exp></and_exp></or_exp>
</condition>

<Node id="8" bw="7" op_0_bw="32" op_1_bw="64" op_2_bw="64">
<![CDATA[
:3 %wp_parameters_addr = getelementptr i32 %wp_parameters, i64 0, i64 108

]]></Node>
<StgValue><ssdm name="wp_parameters_addr"/></StgValue>
</operation>

<operation id="28" st_id="3" stage="1" lat="1">
<core>Sel</core>
<MemPortIdVec></MemPortIdVec>
<condition id="-1">
<or_exp><and_exp></and_exp></or_exp>
</condition>

<Node id="11" bw="32" op_0_bw="1" op_1_bw="32" op_2_bw="32">
<![CDATA[
:6 %z1_min_V = select i1 %icmp_ln878, i32 4272967196, i32 %wp_superpoints_load

]]></Node>
<StgValue><ssdm name="z1_min_V"/></StgValue>
</operation>

<operation id="29" st_id="3" stage="1" lat="1">
<core>NULL</core>
<MemPortIdVec></MemPortIdVec>
<condition id="-1">
<or_exp><and_exp></and_exp></or_exp>
</condition>

<Node id="12" bw="26" op_0_bw="32">
<![CDATA[
:7 %trunc_ln43 = trunc i32 %z1_min_V

]]></Node>
<StgValue><ssdm name="trunc_ln43"/></StgValue>
</operation>

<operation id="30" st_id="3" stage="1" lat="1">
<core>Sel</core>
<MemPortIdVec></MemPortIdVec>
<condition id="-1">
<or_exp><and_exp></and_exp></or_exp>
</condition>

<Node id="15" bw="32" op_0_bw="1" op_1_bw="32" op_2_bw="32">
<![CDATA[
:10 %z1_max_V = select i1 %icmp_ln878_14, i32 %wp_superpoints_load_1, i32 22000100

]]></Node>
<StgValue><ssdm name="z1_max_V"/></StgValue>
</operation>

<operation id="31" st_id="3" stage="1" lat="1">
<core>NULL</core>
<MemPortIdVec></MemPortIdVec>
<condition id="-1">
<or_exp><and_exp></and_exp></or_exp>
</condition>

<Node id="16" bw="26" op_0_bw="32">
<![CDATA[
:11 %trunc_ln44 = trunc i32 %z1_max_V

]]></Node>
<StgValue><ssdm name="trunc_ln44"/></StgValue>
</operation>

<operation id="32" st_id="3" stage="1" lat="1">
<core>Cmp</core>
<MemPortIdVec></MemPortIdVec>
<condition id="-1">
<or_exp><and_exp></and_exp></or_exp>
</condition>

<Node id="17" bw="1" op_0_bw="32" op_1_bw="32">
<![CDATA[
:12 %icmp_ln886 = icmp_sgt  i32 %z1_min_V, i32 %z1_max_V

]]></Node>
<StgValue><ssdm name="icmp_ln886"/></StgValue>
</operation>

<operation id="33" st_id="3" stage="1" lat="1">
<core>Sel</core>
<MemPortIdVec></MemPortIdVec>
<condition id="-1">
<or_exp><and_exp></and_exp></or_exp>
</condition>

<Node id="18" bw="26" op_0_bw="1" op_1_bw="26" op_2_bw="26">
<![CDATA[
:13 %z1_max_V_1 = select i1 %icmp_ln886, i26 23000100, i26 %trunc_ln44

]]></Node>
<StgValue><ssdm name="z1_max_V_1"/></StgValue>
</operation>

<operation id="34" st_id="3" stage="1" lat="1">
<core>NULL</core>
<MemPortIdVec></MemPortIdVec>
<condition id="-1">
<or_exp><and_exp></and_exp></or_exp>
</condition>

<Node id="19" bw="32" op_0_bw="26">
<![CDATA[
:14 %sext_ln46 = sext i26 %z1_max_V_1

]]></Node>
<StgValue><ssdm name="sext_ln46"/></StgValue>
</operation>

<operation id="35" st_id="3" stage="1" lat="1">
<core>Sel</core>
<MemPortIdVec></MemPortIdVec>
<condition id="-1">
<or_exp><and_exp></and_exp></or_exp>
</condition>

<Node id="20" bw="26" op_0_bw="1" op_1_bw="26" op_2_bw="26">
<![CDATA[
:15 %z1_min_V_1 = select i1 %icmp_ln886, i26 23000100, i26 %trunc_ln43

]]></Node>
<StgValue><ssdm name="z1_min_V_1"/></StgValue>
</operation>

<operation id="36" st_id="3" stage="1" lat="1">
<core>NULL</core>
<MemPortIdVec></MemPortIdVec>
<condition id="-1">
<or_exp><and_exp></and_exp></or_exp>
</condition>

<Node id="21" bw="32" op_0_bw="26">
<![CDATA[
:16 %sext_ln43 = sext i26 %z1_min_V_1

]]></Node>
<StgValue><ssdm name="sext_ln43"/></StgValue>
</operation>

<operation id="37" st_id="3" stage="1" lat="1">
<core>RAM</core>
<MemPortIdVec>0 </MemPortIdVec>
<condition id="-1">
<or_exp><and_exp></and_exp></or_exp>
</condition>

<Node id="22" bw="0" op_0_bw="32" op_1_bw="7">
<![CDATA[
:17 %store_ln57 = store i32 0, i7 %wp_parameters_addr

]]></Node>
<StgValue><ssdm name="store_ln57"/></StgValue>
</operation>

<operation id="38" st_id="3" stage="1" lat="1">
<core>NULL</core>
<MemPortIdVec></MemPortIdVec>
<condition id="-1">
<or_exp><and_exp></and_exp></or_exp>
</condition>

<Node id="24" bw="0" op_0_bw="0">
<![CDATA[
:19 %br_ln59 = br void

]]></Node>
<StgValue><ssdm name="br_ln59"/></StgValue>
</operation>
</state>

<state id="4" st_id="4">

<operation id="39" st_id="4" stage="1" lat="1">
<core>NULL</core>
<MemPortIdVec></MemPortIdVec>
<condition id="-1">
<or_exp><and_exp></and_exp></or_exp>
</condition>

<Node id="26" bw="3" op_0_bw="3" op_1_bw="0" op_2_bw="3" op_3_bw="0">
<![CDATA[
:0 %i = phi i3 1, void, i3 %add_ln64, void %.split._crit_edge

]]></Node>
<StgValue><ssdm name="i"/></StgValue>
</operation>

<operation id="40" st_id="4" stage="1" lat="1">
<core>NULL</core>
<MemPortIdVec></MemPortIdVec>
<condition id="-1">
<or_exp><and_exp></and_exp></or_exp>
</condition>

<Node id="27" bw="8" op_0_bw="8" op_1_bw="3" op_2_bw="5">
<![CDATA[
:1 %tmp = bitconcatenate i8 @_ssdm_op_BitConcatenate.i8.i3.i5, i3 %i, i5 0

]]></Node>
<StgValue><ssdm name="tmp"/></StgValue>
</operation>

<operation id="41" st_id="4" stage="1" lat="1">
<core>NULL</core>
<MemPortIdVec></MemPortIdVec>
<condition id="-1">
<or_exp><and_exp></and_exp></or_exp>
</condition>

<Node id="28" bw="8" op_0_bw="8" op_1_bw="8">
<![CDATA[
:2 %or_ln61 = or i8 %tmp, i8 1

]]></Node>
<StgValue><ssdm name="or_ln61"/></StgValue>
</operation>

<operation id="42" st_id="4" stage="1" lat="1">
<core>NULL</core>
<MemPortIdVec></MemPortIdVec>
<condition id="-1">
<or_exp><and_exp></and_exp></or_exp>
</condition>

<Node id="29" bw="64" op_0_bw="64" op_1_bw="56" op_2_bw="8">
<![CDATA[
:3 %tmp_s = bitconcatenate i64 @_ssdm_op_BitConcatenate.i64.i56.i8, i56 0, i8 %or_ln61

]]></Node>
<StgValue><ssdm name="tmp_s"/></StgValue>
</operation>

<operation id="43" st_id="4" stage="1" lat="1">
<core>NULL</core>
<MemPortIdVec></MemPortIdVec>
<condition id="-1">
<or_exp><and_exp></and_exp></or_exp>
</condition>

<Node id="30" bw="8" op_0_bw="32" op_1_bw="64" op_2_bw="64">
<![CDATA[
:4 %wp_superpoints_addr_3 = getelementptr i32 %wp_superpoints, i64 0, i64 %tmp_s

]]></Node>
<StgValue><ssdm name="wp_superpoints_addr_3"/></StgValue>
</operation>

<operation id="44" st_id="4" stage="1" lat="1">
<core>NULL</core>
<MemPortIdVec></MemPortIdVec>
<condition id="-1">
<or_exp><and_exp></and_exp></or_exp>
</condition>

<Node id="31" bw="8" op_0_bw="8" op_1_bw="8">
<![CDATA[
:5 %or_ln62 = or i8 %tmp, i8 31

]]></Node>
<StgValue><ssdm name="or_ln62"/></StgValue>
</operation>

<operation id="45" st_id="4" stage="1" lat="1">
<core>NULL</core>
<MemPortIdVec></MemPortIdVec>
<condition id="-1">
<or_exp><and_exp></and_exp></or_exp>
</condition>

<Node id="32" bw="64" op_0_bw="64" op_1_bw="56" op_2_bw="8">
<![CDATA[
:6 %tmp_24 = bitconcatenate i64 @_ssdm_op_BitConcatenate.i64.i56.i8, i56 0, i8 %or_ln62

]]></Node>
<StgValue><ssdm name="tmp_24"/></StgValue>
</operation>

<operation id="46" st_id="4" stage="1" lat="1">
<core>NULL</core>
<MemPortIdVec></MemPortIdVec>
<condition id="-1">
<or_exp><and_exp></and_exp></or_exp>
</condition>

<Node id="33" bw="8" op_0_bw="32" op_1_bw="64" op_2_bw="64">
<![CDATA[
:7 %wp_superpoints_addr_4 = getelementptr i32 %wp_superpoints, i64 0, i64 %tmp_24

]]></Node>
<StgValue><ssdm name="wp_superpoints_addr_4"/></StgValue>
</operation>

<operation id="47" st_id="4" stage="1" lat="1">
<core>Cmp</core>
<MemPortIdVec></MemPortIdVec>
<condition id="-1">
<or_exp><and_exp></and_exp></or_exp>
</condition>

<Node id="34" bw="1" op_0_bw="3" op_1_bw="3">
<![CDATA[
:8 %icmp_ln59 = icmp_eq  i3 %i, i3 5

]]></Node>
<StgValue><ssdm name="icmp_ln59"/></StgValue>
</operation>

<operation id="48" st_id="4" stage="1" lat="1">
<core>NULL</core>
<MemPortIdVec></MemPortIdVec>
<condition id="-1">
<or_exp><and_exp></and_exp></or_exp>
</condition>

<Node id="35" bw="32" op_0_bw="32" op_1_bw="64" op_2_bw="64" op_3_bw="64">
<![CDATA[
:9 %empty_80 = speclooptripcount i32 @_ssdm_op_SpecLoopTripCount, i64 4, i64 4, i64 4

]]></Node>
<StgValue><ssdm name="empty_80"/></StgValue>
</operation>

<operation id="49" st_id="4" stage="1" lat="1">
<core>NULL</core>
<MemPortIdVec></MemPortIdVec>
<condition id="-1">
<or_exp><and_exp></and_exp></or_exp>
</condition>

<Node id="36" bw="0" op_0_bw="1" op_1_bw="0" op_2_bw="0">
<![CDATA[
:10 %br_ln59 = br i1 %icmp_ln59, void %.split, void

]]></Node>
<StgValue><ssdm name="br_ln59"/></StgValue>
</operation>

<operation id="50" st_id="4" stage="2" lat="2">
<core>RAM</core>
<MemPortIdVec>1 </MemPortIdVec>
<condition id="-1">
<or_exp><and_exp><literal name="icmp_ln59" val="0"/>
</and_exp></or_exp>
</condition>

<Node id="41" bw="32" op_0_bw="8">
<![CDATA[
.split:3 %wp_superpoints_load_2 = load i8 %wp_superpoints_addr_3

]]></Node>
<StgValue><ssdm name="wp_superpoints_load_2"/></StgValue>
</operation>

<operation id="51" st_id="4" stage="2" lat="2">
<core>RAM</core>
<MemPortIdVec>0 </MemPortIdVec>
<condition id="-1">
<or_exp><and_exp><literal name="icmp_ln59" val="0"/>
</and_exp></or_exp>
</condition>

<Node id="42" bw="32" op_0_bw="8">
<![CDATA[
.split:4 %wp_superpoints_load_3 = load i8 %wp_superpoints_addr_4

]]></Node>
<StgValue><ssdm name="wp_superpoints_load_3"/></StgValue>
</operation>

<operation id="52" st_id="4" stage="1" lat="1">
<core>NULL</core>
<MemPortIdVec></MemPortIdVec>
<condition id="-1">
<or_exp><and_exp><literal name="icmp_ln59" val="1"/>
</and_exp></or_exp>
</condition>

<Node id="104" bw="0">
<![CDATA[
:0 %ret_ln82 = ret

]]></Node>
<StgValue><ssdm name="ret_ln82"/></StgValue>
</operation>
</state>

<state id="5" st_id="5">

<operation id="53" st_id="5" stage="1" lat="1">
<core>Adder</core>
<MemPortIdVec></MemPortIdVec>
<condition id="-1">
<or_exp><and_exp></and_exp></or_exp>
</condition>

<Node id="38" bw="3" op_0_bw="3" op_1_bw="3">
<![CDATA[
.split:0 %add_ln64 = add i3 %i, i3 1

]]></Node>
<StgValue><ssdm name="add_ln64"/></StgValue>
</operation>

<operation id="54" st_id="5" stage="1" lat="2">
<core>RAM</core>
<MemPortIdVec>1 </MemPortIdVec>
<condition id="-1">
<or_exp><and_exp></and_exp></or_exp>
</condition>

<Node id="41" bw="32" op_0_bw="8">
<![CDATA[
.split:3 %wp_superpoints_load_2 = load i8 %wp_superpoints_addr_3

]]></Node>
<StgValue><ssdm name="wp_superpoints_load_2"/></StgValue>
</operation>

<operation id="55" st_id="5" stage="1" lat="2">
<core>RAM</core>
<MemPortIdVec>0 </MemPortIdVec>
<condition id="-1">
<or_exp><and_exp></and_exp></or_exp>
</condition>

<Node id="42" bw="32" op_0_bw="8">
<![CDATA[
.split:4 %wp_superpoints_load_3 = load i8 %wp_superpoints_addr_4

]]></Node>
<StgValue><ssdm name="wp_superpoints_load_3"/></StgValue>
</operation>
</state>

<state id="6" st_id="6">

<operation id="56" st_id="6" stage="7" lat="7">
<core></core>
<MemPortIdVec></MemPortIdVec>
<condition id="-1">
<or_exp><and_exp></and_exp></or_exp>
</condition>

<Node id="43" bw="32" op_0_bw="32" op_1_bw="32" op_2_bw="32" op_3_bw="3" op_4_bw="3" op_5_bw="3" op_6_bw="35">
<![CDATA[
.split:5 %a_V = call i32 @straightLineProjectorFromLayerIJtoK, i32 %sext_ln43, i32 %wp_superpoints_load_3, i3 1, i3 %add_ln64, i3 5, i35 %radiiDivisionList

]]></Node>
<StgValue><ssdm name="a_V"/></StgValue>
</operation>

<operation id="57" st_id="6" stage="7" lat="7">
<core></core>
<MemPortIdVec></MemPortIdVec>
<condition id="-1">
<or_exp><and_exp></and_exp></or_exp>
</condition>

<Node id="44" bw="32" op_0_bw="32" op_1_bw="32" op_2_bw="32" op_3_bw="3" op_4_bw="3" op_5_bw="3" op_6_bw="35">
<![CDATA[
.split:6 %b_V = call i32 @straightLineProjectorFromLayerIJtoK, i32 %sext_ln46, i32 %wp_superpoints_load_3, i3 1, i3 %add_ln64, i3 5, i35 %radiiDivisionList

]]></Node>
<StgValue><ssdm name="b_V"/></StgValue>
</operation>

<operation id="58" st_id="6" stage="7" lat="7">
<core></core>
<MemPortIdVec></MemPortIdVec>
<condition id="-1">
<or_exp><and_exp></and_exp></or_exp>
</condition>

<Node id="45" bw="32" op_0_bw="32" op_1_bw="32" op_2_bw="32" op_3_bw="3" op_4_bw="3" op_5_bw="3" op_6_bw="35">
<![CDATA[
.split:7 %c_V = call i32 @straightLineProjectorFromLayerIJtoK, i32 %sext_ln43, i32 %wp_superpoints_load_2, i3 1, i3 %add_ln64, i3 5, i35 %radiiDivisionList

]]></Node>
<StgValue><ssdm name="c_V"/></StgValue>
</operation>

<operation id="59" st_id="6" stage="7" lat="7">
<core></core>
<MemPortIdVec></MemPortIdVec>
<condition id="-1">
<or_exp><and_exp></and_exp></or_exp>
</condition>

<Node id="46" bw="32" op_0_bw="32" op_1_bw="32" op_2_bw="32" op_3_bw="3" op_4_bw="3" op_5_bw="3" op_6_bw="35">
<![CDATA[
.split:8 %d_V = call i32 @straightLineProjectorFromLayerIJtoK, i32 %sext_ln46, i32 %wp_superpoints_load_2, i3 1, i3 %add_ln64, i3 5, i35 %radiiDivisionList

]]></Node>
<StgValue><ssdm name="d_V"/></StgValue>
</operation>
</state>

<state id="7" st_id="7">

<operation id="60" st_id="7" stage="6" lat="7">
<core></core>
<MemPortIdVec></MemPortIdVec>
<condition id="-1">
<or_exp><and_exp></and_exp></or_exp>
</condition>

<Node id="43" bw="32" op_0_bw="32" op_1_bw="32" op_2_bw="32" op_3_bw="3" op_4_bw="3" op_5_bw="3" op_6_bw="35">
<![CDATA[
.split:5 %a_V = call i32 @straightLineProjectorFromLayerIJtoK, i32 %sext_ln43, i32 %wp_superpoints_load_3, i3 1, i3 %add_ln64, i3 5, i35 %radiiDivisionList

]]></Node>
<StgValue><ssdm name="a_V"/></StgValue>
</operation>

<operation id="61" st_id="7" stage="6" lat="7">
<core></core>
<MemPortIdVec></MemPortIdVec>
<condition id="-1">
<or_exp><and_exp></and_exp></or_exp>
</condition>

<Node id="44" bw="32" op_0_bw="32" op_1_bw="32" op_2_bw="32" op_3_bw="3" op_4_bw="3" op_5_bw="3" op_6_bw="35">
<![CDATA[
.split:6 %b_V = call i32 @straightLineProjectorFromLayerIJtoK, i32 %sext_ln46, i32 %wp_superpoints_load_3, i3 1, i3 %add_ln64, i3 5, i35 %radiiDivisionList

]]></Node>
<StgValue><ssdm name="b_V"/></StgValue>
</operation>

<operation id="62" st_id="7" stage="6" lat="7">
<core></core>
<MemPortIdVec></MemPortIdVec>
<condition id="-1">
<or_exp><and_exp></and_exp></or_exp>
</condition>

<Node id="45" bw="32" op_0_bw="32" op_1_bw="32" op_2_bw="32" op_3_bw="3" op_4_bw="3" op_5_bw="3" op_6_bw="35">
<![CDATA[
.split:7 %c_V = call i32 @straightLineProjectorFromLayerIJtoK, i32 %sext_ln43, i32 %wp_superpoints_load_2, i3 1, i3 %add_ln64, i3 5, i35 %radiiDivisionList

]]></Node>
<StgValue><ssdm name="c_V"/></StgValue>
</operation>

<operation id="63" st_id="7" stage="6" lat="7">
<core></core>
<MemPortIdVec></MemPortIdVec>
<condition id="-1">
<or_exp><and_exp></and_exp></or_exp>
</condition>

<Node id="46" bw="32" op_0_bw="32" op_1_bw="32" op_2_bw="32" op_3_bw="3" op_4_bw="3" op_5_bw="3" op_6_bw="35">
<![CDATA[
.split:8 %d_V = call i32 @straightLineProjectorFromLayerIJtoK, i32 %sext_ln46, i32 %wp_superpoints_load_2, i3 1, i3 %add_ln64, i3 5, i35 %radiiDivisionList

]]></Node>
<StgValue><ssdm name="d_V"/></StgValue>
</operation>
</state>

<state id="8" st_id="8">

<operation id="64" st_id="8" stage="5" lat="7">
<core></core>
<MemPortIdVec></MemPortIdVec>
<condition id="-1">
<or_exp><and_exp></and_exp></or_exp>
</condition>

<Node id="43" bw="32" op_0_bw="32" op_1_bw="32" op_2_bw="32" op_3_bw="3" op_4_bw="3" op_5_bw="3" op_6_bw="35">
<![CDATA[
.split:5 %a_V = call i32 @straightLineProjectorFromLayerIJtoK, i32 %sext_ln43, i32 %wp_superpoints_load_3, i3 1, i3 %add_ln64, i3 5, i35 %radiiDivisionList

]]></Node>
<StgValue><ssdm name="a_V"/></StgValue>
</operation>

<operation id="65" st_id="8" stage="5" lat="7">
<core></core>
<MemPortIdVec></MemPortIdVec>
<condition id="-1">
<or_exp><and_exp></and_exp></or_exp>
</condition>

<Node id="44" bw="32" op_0_bw="32" op_1_bw="32" op_2_bw="32" op_3_bw="3" op_4_bw="3" op_5_bw="3" op_6_bw="35">
<![CDATA[
.split:6 %b_V = call i32 @straightLineProjectorFromLayerIJtoK, i32 %sext_ln46, i32 %wp_superpoints_load_3, i3 1, i3 %add_ln64, i3 5, i35 %radiiDivisionList

]]></Node>
<StgValue><ssdm name="b_V"/></StgValue>
</operation>

<operation id="66" st_id="8" stage="5" lat="7">
<core></core>
<MemPortIdVec></MemPortIdVec>
<condition id="-1">
<or_exp><and_exp></and_exp></or_exp>
</condition>

<Node id="45" bw="32" op_0_bw="32" op_1_bw="32" op_2_bw="32" op_3_bw="3" op_4_bw="3" op_5_bw="3" op_6_bw="35">
<![CDATA[
.split:7 %c_V = call i32 @straightLineProjectorFromLayerIJtoK, i32 %sext_ln43, i32 %wp_superpoints_load_2, i3 1, i3 %add_ln64, i3 5, i35 %radiiDivisionList

]]></Node>
<StgValue><ssdm name="c_V"/></StgValue>
</operation>

<operation id="67" st_id="8" stage="5" lat="7">
<core></core>
<MemPortIdVec></MemPortIdVec>
<condition id="-1">
<or_exp><and_exp></and_exp></or_exp>
</condition>

<Node id="46" bw="32" op_0_bw="32" op_1_bw="32" op_2_bw="32" op_3_bw="3" op_4_bw="3" op_5_bw="3" op_6_bw="35">
<![CDATA[
.split:8 %d_V = call i32 @straightLineProjectorFromLayerIJtoK, i32 %sext_ln46, i32 %wp_superpoints_load_2, i3 1, i3 %add_ln64, i3 5, i35 %radiiDivisionList

]]></Node>
<StgValue><ssdm name="d_V"/></StgValue>
</operation>
</state>

<state id="9" st_id="9">

<operation id="68" st_id="9" stage="4" lat="7">
<core></core>
<MemPortIdVec></MemPortIdVec>
<condition id="-1">
<or_exp><and_exp></and_exp></or_exp>
</condition>

<Node id="43" bw="32" op_0_bw="32" op_1_bw="32" op_2_bw="32" op_3_bw="3" op_4_bw="3" op_5_bw="3" op_6_bw="35">
<![CDATA[
.split:5 %a_V = call i32 @straightLineProjectorFromLayerIJtoK, i32 %sext_ln43, i32 %wp_superpoints_load_3, i3 1, i3 %add_ln64, i3 5, i35 %radiiDivisionList

]]></Node>
<StgValue><ssdm name="a_V"/></StgValue>
</operation>

<operation id="69" st_id="9" stage="4" lat="7">
<core></core>
<MemPortIdVec></MemPortIdVec>
<condition id="-1">
<or_exp><and_exp></and_exp></or_exp>
</condition>

<Node id="44" bw="32" op_0_bw="32" op_1_bw="32" op_2_bw="32" op_3_bw="3" op_4_bw="3" op_5_bw="3" op_6_bw="35">
<![CDATA[
.split:6 %b_V = call i32 @straightLineProjectorFromLayerIJtoK, i32 %sext_ln46, i32 %wp_superpoints_load_3, i3 1, i3 %add_ln64, i3 5, i35 %radiiDivisionList

]]></Node>
<StgValue><ssdm name="b_V"/></StgValue>
</operation>

<operation id="70" st_id="9" stage="4" lat="7">
<core></core>
<MemPortIdVec></MemPortIdVec>
<condition id="-1">
<or_exp><and_exp></and_exp></or_exp>
</condition>

<Node id="45" bw="32" op_0_bw="32" op_1_bw="32" op_2_bw="32" op_3_bw="3" op_4_bw="3" op_5_bw="3" op_6_bw="35">
<![CDATA[
.split:7 %c_V = call i32 @straightLineProjectorFromLayerIJtoK, i32 %sext_ln43, i32 %wp_superpoints_load_2, i3 1, i3 %add_ln64, i3 5, i35 %radiiDivisionList

]]></Node>
<StgValue><ssdm name="c_V"/></StgValue>
</operation>

<operation id="71" st_id="9" stage="4" lat="7">
<core></core>
<MemPortIdVec></MemPortIdVec>
<condition id="-1">
<or_exp><and_exp></and_exp></or_exp>
</condition>

<Node id="46" bw="32" op_0_bw="32" op_1_bw="32" op_2_bw="32" op_3_bw="3" op_4_bw="3" op_5_bw="3" op_6_bw="35">
<![CDATA[
.split:8 %d_V = call i32 @straightLineProjectorFromLayerIJtoK, i32 %sext_ln46, i32 %wp_superpoints_load_2, i3 1, i3 %add_ln64, i3 5, i35 %radiiDivisionList

]]></Node>
<StgValue><ssdm name="d_V"/></StgValue>
</operation>
</state>

<state id="10" st_id="10">

<operation id="72" st_id="10" stage="3" lat="7">
<core></core>
<MemPortIdVec></MemPortIdVec>
<condition id="-1">
<or_exp><and_exp></and_exp></or_exp>
</condition>

<Node id="43" bw="32" op_0_bw="32" op_1_bw="32" op_2_bw="32" op_3_bw="3" op_4_bw="3" op_5_bw="3" op_6_bw="35">
<![CDATA[
.split:5 %a_V = call i32 @straightLineProjectorFromLayerIJtoK, i32 %sext_ln43, i32 %wp_superpoints_load_3, i3 1, i3 %add_ln64, i3 5, i35 %radiiDivisionList

]]></Node>
<StgValue><ssdm name="a_V"/></StgValue>
</operation>

<operation id="73" st_id="10" stage="3" lat="7">
<core></core>
<MemPortIdVec></MemPortIdVec>
<condition id="-1">
<or_exp><and_exp></and_exp></or_exp>
</condition>

<Node id="44" bw="32" op_0_bw="32" op_1_bw="32" op_2_bw="32" op_3_bw="3" op_4_bw="3" op_5_bw="3" op_6_bw="35">
<![CDATA[
.split:6 %b_V = call i32 @straightLineProjectorFromLayerIJtoK, i32 %sext_ln46, i32 %wp_superpoints_load_3, i3 1, i3 %add_ln64, i3 5, i35 %radiiDivisionList

]]></Node>
<StgValue><ssdm name="b_V"/></StgValue>
</operation>

<operation id="74" st_id="10" stage="3" lat="7">
<core></core>
<MemPortIdVec></MemPortIdVec>
<condition id="-1">
<or_exp><and_exp></and_exp></or_exp>
</condition>

<Node id="45" bw="32" op_0_bw="32" op_1_bw="32" op_2_bw="32" op_3_bw="3" op_4_bw="3" op_5_bw="3" op_6_bw="35">
<![CDATA[
.split:7 %c_V = call i32 @straightLineProjectorFromLayerIJtoK, i32 %sext_ln43, i32 %wp_superpoints_load_2, i3 1, i3 %add_ln64, i3 5, i35 %radiiDivisionList

]]></Node>
<StgValue><ssdm name="c_V"/></StgValue>
</operation>

<operation id="75" st_id="10" stage="3" lat="7">
<core></core>
<MemPortIdVec></MemPortIdVec>
<condition id="-1">
<or_exp><and_exp></and_exp></or_exp>
</condition>

<Node id="46" bw="32" op_0_bw="32" op_1_bw="32" op_2_bw="32" op_3_bw="3" op_4_bw="3" op_5_bw="3" op_6_bw="35">
<![CDATA[
.split:8 %d_V = call i32 @straightLineProjectorFromLayerIJtoK, i32 %sext_ln46, i32 %wp_superpoints_load_2, i3 1, i3 %add_ln64, i3 5, i35 %radiiDivisionList

]]></Node>
<StgValue><ssdm name="d_V"/></StgValue>
</operation>
</state>

<state id="11" st_id="11">

<operation id="76" st_id="11" stage="2" lat="7">
<core></core>
<MemPortIdVec></MemPortIdVec>
<condition id="-1">
<or_exp><and_exp></and_exp></or_exp>
</condition>

<Node id="43" bw="32" op_0_bw="32" op_1_bw="32" op_2_bw="32" op_3_bw="3" op_4_bw="3" op_5_bw="3" op_6_bw="35">
<![CDATA[
.split:5 %a_V = call i32 @straightLineProjectorFromLayerIJtoK, i32 %sext_ln43, i32 %wp_superpoints_load_3, i3 1, i3 %add_ln64, i3 5, i35 %radiiDivisionList

]]></Node>
<StgValue><ssdm name="a_V"/></StgValue>
</operation>

<operation id="77" st_id="11" stage="2" lat="7">
<core></core>
<MemPortIdVec></MemPortIdVec>
<condition id="-1">
<or_exp><and_exp></and_exp></or_exp>
</condition>

<Node id="44" bw="32" op_0_bw="32" op_1_bw="32" op_2_bw="32" op_3_bw="3" op_4_bw="3" op_5_bw="3" op_6_bw="35">
<![CDATA[
.split:6 %b_V = call i32 @straightLineProjectorFromLayerIJtoK, i32 %sext_ln46, i32 %wp_superpoints_load_3, i3 1, i3 %add_ln64, i3 5, i35 %radiiDivisionList

]]></Node>
<StgValue><ssdm name="b_V"/></StgValue>
</operation>

<operation id="78" st_id="11" stage="2" lat="7">
<core></core>
<MemPortIdVec></MemPortIdVec>
<condition id="-1">
<or_exp><and_exp></and_exp></or_exp>
</condition>

<Node id="45" bw="32" op_0_bw="32" op_1_bw="32" op_2_bw="32" op_3_bw="3" op_4_bw="3" op_5_bw="3" op_6_bw="35">
<![CDATA[
.split:7 %c_V = call i32 @straightLineProjectorFromLayerIJtoK, i32 %sext_ln43, i32 %wp_superpoints_load_2, i3 1, i3 %add_ln64, i3 5, i35 %radiiDivisionList

]]></Node>
<StgValue><ssdm name="c_V"/></StgValue>
</operation>

<operation id="79" st_id="11" stage="2" lat="7">
<core></core>
<MemPortIdVec></MemPortIdVec>
<condition id="-1">
<or_exp><and_exp></and_exp></or_exp>
</condition>

<Node id="46" bw="32" op_0_bw="32" op_1_bw="32" op_2_bw="32" op_3_bw="3" op_4_bw="3" op_5_bw="3" op_6_bw="35">
<![CDATA[
.split:8 %d_V = call i32 @straightLineProjectorFromLayerIJtoK, i32 %sext_ln46, i32 %wp_superpoints_load_2, i3 1, i3 %add_ln64, i3 5, i35 %radiiDivisionList

]]></Node>
<StgValue><ssdm name="d_V"/></StgValue>
</operation>
</state>

<state id="12" st_id="12">

<operation id="80" st_id="12" stage="1" lat="1">
<core>NULL</core>
<MemPortIdVec></MemPortIdVec>
<condition id="-1">
<or_exp><and_exp></and_exp></or_exp>
</condition>

<Node id="39" bw="32" op_0_bw="32" op_1_bw="0">
<![CDATA[
.split:1 %p_load84 = load i32 %empty

]]></Node>
<StgValue><ssdm name="p_load84"/></StgValue>
</operation>

<operation id="81" st_id="12" stage="1" lat="1">
<core>NULL</core>
<MemPortIdVec></MemPortIdVec>
<condition id="-1">
<or_exp><and_exp></and_exp></or_exp>
</condition>

<Node id="40" bw="0" op_0_bw="0" op_1_bw="0">
<![CDATA[
.split:2 %specloopname_ln59 = specloopname void @_ssdm_op_SpecLoopName, void @empty_11

]]></Node>
<StgValue><ssdm name="specloopname_ln59"/></StgValue>
</operation>

<operation id="82" st_id="12" stage="1" lat="7">
<core></core>
<MemPortIdVec></MemPortIdVec>
<condition id="-1">
<or_exp><and_exp></and_exp></or_exp>
</condition>

<Node id="43" bw="32" op_0_bw="32" op_1_bw="32" op_2_bw="32" op_3_bw="3" op_4_bw="3" op_5_bw="3" op_6_bw="35">
<![CDATA[
.split:5 %a_V = call i32 @straightLineProjectorFromLayerIJtoK, i32 %sext_ln43, i32 %wp_superpoints_load_3, i3 1, i3 %add_ln64, i3 5, i35 %radiiDivisionList

]]></Node>
<StgValue><ssdm name="a_V"/></StgValue>
</operation>

<operation id="83" st_id="12" stage="1" lat="7">
<core></core>
<MemPortIdVec></MemPortIdVec>
<condition id="-1">
<or_exp><and_exp></and_exp></or_exp>
</condition>

<Node id="44" bw="32" op_0_bw="32" op_1_bw="32" op_2_bw="32" op_3_bw="3" op_4_bw="3" op_5_bw="3" op_6_bw="35">
<![CDATA[
.split:6 %b_V = call i32 @straightLineProjectorFromLayerIJtoK, i32 %sext_ln46, i32 %wp_superpoints_load_3, i3 1, i3 %add_ln64, i3 5, i35 %radiiDivisionList

]]></Node>
<StgValue><ssdm name="b_V"/></StgValue>
</operation>

<operation id="84" st_id="12" stage="1" lat="7">
<core></core>
<MemPortIdVec></MemPortIdVec>
<condition id="-1">
<or_exp><and_exp></and_exp></or_exp>
</condition>

<Node id="45" bw="32" op_0_bw="32" op_1_bw="32" op_2_bw="32" op_3_bw="3" op_4_bw="3" op_5_bw="3" op_6_bw="35">
<![CDATA[
.split:7 %c_V = call i32 @straightLineProjectorFromLayerIJtoK, i32 %sext_ln43, i32 %wp_superpoints_load_2, i3 1, i3 %add_ln64, i3 5, i35 %radiiDivisionList

]]></Node>
<StgValue><ssdm name="c_V"/></StgValue>
</operation>

<operation id="85" st_id="12" stage="1" lat="7">
<core></core>
<MemPortIdVec></MemPortIdVec>
<condition id="-1">
<or_exp><and_exp></and_exp></or_exp>
</condition>

<Node id="46" bw="32" op_0_bw="32" op_1_bw="32" op_2_bw="32" op_3_bw="3" op_4_bw="3" op_5_bw="3" op_6_bw="35">
<![CDATA[
.split:8 %d_V = call i32 @straightLineProjectorFromLayerIJtoK, i32 %sext_ln46, i32 %wp_superpoints_load_2, i3 1, i3 %add_ln64, i3 5, i35 %radiiDivisionList

]]></Node>
<StgValue><ssdm name="d_V"/></StgValue>
</operation>

<operation id="86" st_id="12" stage="1" lat="1">
<core>NULL</core>
<MemPortIdVec></MemPortIdVec>
<condition id="-1">
<or_exp><and_exp></and_exp></or_exp>
</condition>

<Node id="47" bw="30" op_0_bw="30" op_1_bw="32" op_2_bw="32" op_3_bw="32">
<![CDATA[
.split:9 %tmp_28 = partselect i30 @_ssdm_op_PartSelect.i30.i32.i32.i32, i32 %p_load84, i32 2, i32 31

]]></Node>
<StgValue><ssdm name="tmp_28"/></StgValue>
</operation>

<operation id="87" st_id="12" stage="1" lat="1">
<core>Cmp</core>
<MemPortIdVec></MemPortIdVec>
<condition id="-1">
<or_exp><and_exp></and_exp></or_exp>
</condition>

<Node id="48" bw="1" op_0_bw="30" op_1_bw="30">
<![CDATA[
.split:10 %icmp_ln70 = icmp_slt  i30 %tmp_28, i30 1

]]></Node>
<StgValue><ssdm name="icmp_ln70"/></StgValue>
</operation>

<operation id="88" st_id="12" stage="1" lat="1">
<core>NULL</core>
<MemPortIdVec></MemPortIdVec>
<condition id="-1">
<or_exp><and_exp></and_exp></or_exp>
</condition>

<Node id="49" bw="0" op_0_bw="1" op_1_bw="0" op_2_bw="0">
<![CDATA[
.split:11 %br_ln70 = br i1 %icmp_ln70, void %.split._crit_edge, void

]]></Node>
<StgValue><ssdm name="br_ln70"/></StgValue>
</operation>

<operation id="89" st_id="12" stage="1" lat="1">
<core>NULL</core>
<MemPortIdVec></MemPortIdVec>
<condition id="-1">
<or_exp><and_exp><literal name="icmp_ln70" val="1"/>
</and_exp></or_exp>
</condition>

<Node id="51" bw="4" op_0_bw="32">
<![CDATA[
:0 %trunc_ln72 = trunc i32 %p_load84

]]></Node>
<StgValue><ssdm name="trunc_ln72"/></StgValue>
</operation>

<operation id="90" st_id="12" stage="1" lat="1">
<core>NULL</core>
<MemPortIdVec></MemPortIdVec>
<condition id="-1">
<or_exp><and_exp><literal name="icmp_ln70" val="1"/>
</and_exp></or_exp>
</condition>

<Node id="52" bw="7" op_0_bw="7" op_1_bw="4" op_2_bw="3">
<![CDATA[
:1 %tmp_57_cast = bitconcatenate i7 @_ssdm_op_BitConcatenate.i7.i4.i3, i4 %trunc_ln72, i3 0

]]></Node>
<StgValue><ssdm name="tmp_57_cast"/></StgValue>
</operation>

<operation id="91" st_id="12" stage="1" lat="1">
<core>NULL</core>
<MemPortIdVec></MemPortIdVec>
<condition id="-1">
<or_exp><and_exp><literal name="icmp_ln70" val="1"/>
</and_exp></or_exp>
</condition>

<Node id="53" bw="6" op_0_bw="32">
<![CDATA[
:2 %trunc_ln72_1 = trunc i32 %p_load84

]]></Node>
<StgValue><ssdm name="trunc_ln72_1"/></StgValue>
</operation>

<operation id="92" st_id="12" stage="1" lat="1">
<core>NULL</core>
<MemPortIdVec></MemPortIdVec>
<condition id="-1">
<or_exp><and_exp><literal name="icmp_ln70" val="1"/>
</and_exp></or_exp>
</condition>

<Node id="54" bw="7" op_0_bw="7" op_1_bw="6" op_2_bw="1">
<![CDATA[
:3 %tmp_58_cast = bitconcatenate i7 @_ssdm_op_BitConcatenate.i7.i6.i1, i6 %trunc_ln72_1, i1 0

]]></Node>
<StgValue><ssdm name="tmp_58_cast"/></StgValue>
</operation>

<operation id="93" st_id="12" stage="1" lat="1">
<core>Adder</core>
<MemPortIdVec></MemPortIdVec>
<condition id="-1">
<or_exp><and_exp><literal name="icmp_ln70" val="1"/>
</and_exp></or_exp>
</condition>

<Node id="55" bw="7" op_0_bw="7" op_1_bw="7">
<![CDATA[
:4 %sub_ln72 = sub i7 %tmp_57_cast, i7 %tmp_58_cast

]]></Node>
<StgValue><ssdm name="sub_ln72"/></StgValue>
</operation>

<operation id="94" st_id="12" stage="2" lat="2">
<core>RAM</core>
<MemPortIdVec>1 </MemPortIdVec>
<condition id="-1">
<or_exp><and_exp><literal name="icmp_ln70" val="1"/>
</and_exp></or_exp>
</condition>

<Node id="59" bw="32" op_0_bw="7">
<![CDATA[
:8 %wp_parameters_load = load i7 %wp_parameters_addr

]]></Node>
<StgValue><ssdm name="wp_parameters_load"/></StgValue>
</operation>

<operation id="95" st_id="12" stage="2" lat="2">
<core>RAM</core>
<MemPortIdVec>0 </MemPortIdVec>
<condition id="-1">
<or_exp><and_exp><literal name="icmp_ln70" val="1"/>
</and_exp></or_exp>
</condition>

<Node id="73" bw="32" op_0_bw="7">
<![CDATA[
:22 %wp_parameters_load_13 = load i7 %wp_parameters_addr

]]></Node>
<StgValue><ssdm name="wp_parameters_load_13"/></StgValue>
</operation>
</state>

<state id="13" st_id="13">

<operation id="96" st_id="13" stage="1" lat="1">
<core>NULL</core>
<MemPortIdVec></MemPortIdVec>
<condition id="-1">
<or_exp><and_exp></and_exp></or_exp>
</condition>

<Node id="56" bw="64" op_0_bw="7">
<![CDATA[
:5 %zext_ln72 = zext i7 %sub_ln72

]]></Node>
<StgValue><ssdm name="zext_ln72"/></StgValue>
</operation>

<operation id="97" st_id="13" stage="1" lat="1">
<core>NULL</core>
<MemPortIdVec></MemPortIdVec>
<condition id="-1">
<or_exp><and_exp></and_exp></or_exp>
</condition>

<Node id="57" bw="7" op_0_bw="32" op_1_bw="64" op_2_bw="64">
<![CDATA[
:6 %wp_parameters_addr_30 = getelementptr i32 %wp_parameters, i64 0, i64 %zext_ln72

]]></Node>
<StgValue><ssdm name="wp_parameters_addr_30"/></StgValue>
</operation>

<operation id="98" st_id="13" stage="1" lat="1">
<core>RAM</core>
<MemPortIdVec>1 </MemPortIdVec>
<condition id="-1">
<or_exp><and_exp></and_exp></or_exp>
</condition>

<Node id="58" bw="0" op_0_bw="32" op_1_bw="7">
<![CDATA[
:7 %store_ln72 = store i32 %a_V, i7 %wp_parameters_addr_30

]]></Node>
<StgValue><ssdm name="store_ln72"/></StgValue>
</operation>

<operation id="99" st_id="13" stage="1" lat="2">
<core>RAM</core>
<MemPortIdVec>1 </MemPortIdVec>
<condition id="-1">
<or_exp><and_exp></and_exp></or_exp>
</condition>

<Node id="59" bw="32" op_0_bw="7">
<![CDATA[
:8 %wp_parameters_load = load i7 %wp_parameters_addr

]]></Node>
<StgValue><ssdm name="wp_parameters_load"/></StgValue>
</operation>

<operation id="100" st_id="13" stage="1" lat="1">
<core>NULL</core>
<MemPortIdVec></MemPortIdVec>
<condition id="-1">
<or_exp><and_exp></and_exp></or_exp>
</condition>

<Node id="60" bw="4" op_0_bw="32">
<![CDATA[
:9 %trunc_ln73 = trunc i32 %wp_parameters_load

]]></Node>
<StgValue><ssdm name="trunc_ln73"/></StgValue>
</operation>

<operation id="101" st_id="13" stage="1" lat="1">
<core>NULL</core>
<MemPortIdVec></MemPortIdVec>
<condition id="-1">
<or_exp><and_exp></and_exp></or_exp>
</condition>

<Node id="61" bw="7" op_0_bw="7" op_1_bw="4" op_2_bw="3">
<![CDATA[
:10 %tmp_59_cast = bitconcatenate i7 @_ssdm_op_BitConcatenate.i7.i4.i3, i4 %trunc_ln73, i3 0

]]></Node>
<StgValue><ssdm name="tmp_59_cast"/></StgValue>
</operation>

<operation id="102" st_id="13" stage="1" lat="1">
<core>NULL</core>
<MemPortIdVec></MemPortIdVec>
<condition id="-1">
<or_exp><and_exp></and_exp></or_exp>
</condition>

<Node id="62" bw="6" op_0_bw="32">
<![CDATA[
:11 %trunc_ln73_1 = trunc i32 %wp_parameters_load

]]></Node>
<StgValue><ssdm name="trunc_ln73_1"/></StgValue>
</operation>

<operation id="103" st_id="13" stage="1" lat="1">
<core>NULL</core>
<MemPortIdVec></MemPortIdVec>
<condition id="-1">
<or_exp><and_exp></and_exp></or_exp>
</condition>

<Node id="63" bw="7" op_0_bw="7" op_1_bw="6" op_2_bw="1">
<![CDATA[
:12 %tmp_60_cast = bitconcatenate i7 @_ssdm_op_BitConcatenate.i7.i6.i1, i6 %trunc_ln73_1, i1 0

]]></Node>
<StgValue><ssdm name="tmp_60_cast"/></StgValue>
</operation>

<operation id="104" st_id="13" stage="1" lat="1">
<core>Adder</core>
<MemPortIdVec></MemPortIdVec>
<condition id="-1">
<or_exp><and_exp></and_exp></or_exp>
</condition>

<Node id="64" bw="7" op_0_bw="7" op_1_bw="7">
<![CDATA[
:13 %sub_ln73 = sub i7 %tmp_59_cast, i7 %tmp_60_cast

]]></Node>
<StgValue><ssdm name="sub_ln73"/></StgValue>
</operation>

<operation id="105" st_id="13" stage="1" lat="2">
<core>RAM</core>
<MemPortIdVec>0 </MemPortIdVec>
<condition id="-1">
<or_exp><and_exp></and_exp></or_exp>
</condition>

<Node id="73" bw="32" op_0_bw="7">
<![CDATA[
:22 %wp_parameters_load_13 = load i7 %wp_parameters_addr

]]></Node>
<StgValue><ssdm name="wp_parameters_load_13"/></StgValue>
</operation>

<operation id="106" st_id="13" stage="1" lat="1">
<core>NULL</core>
<MemPortIdVec></MemPortIdVec>
<condition id="-1">
<or_exp><and_exp></and_exp></or_exp>
</condition>

<Node id="74" bw="4" op_0_bw="32">
<![CDATA[
:23 %trunc_ln75 = trunc i32 %wp_parameters_load_13

]]></Node>
<StgValue><ssdm name="trunc_ln75"/></StgValue>
</operation>

<operation id="107" st_id="13" stage="1" lat="1">
<core>NULL</core>
<MemPortIdVec></MemPortIdVec>
<condition id="-1">
<or_exp><and_exp></and_exp></or_exp>
</condition>

<Node id="75" bw="7" op_0_bw="7" op_1_bw="4" op_2_bw="3">
<![CDATA[
:24 %tmp_61_cast = bitconcatenate i7 @_ssdm_op_BitConcatenate.i7.i4.i3, i4 %trunc_ln75, i3 0

]]></Node>
<StgValue><ssdm name="tmp_61_cast"/></StgValue>
</operation>

<operation id="108" st_id="13" stage="1" lat="1">
<core>NULL</core>
<MemPortIdVec></MemPortIdVec>
<condition id="-1">
<or_exp><and_exp></and_exp></or_exp>
</condition>

<Node id="76" bw="6" op_0_bw="32">
<![CDATA[
:25 %trunc_ln75_1 = trunc i32 %wp_parameters_load_13

]]></Node>
<StgValue><ssdm name="trunc_ln75_1"/></StgValue>
</operation>

<operation id="109" st_id="13" stage="1" lat="1">
<core>NULL</core>
<MemPortIdVec></MemPortIdVec>
<condition id="-1">
<or_exp><and_exp></and_exp></or_exp>
</condition>

<Node id="77" bw="7" op_0_bw="7" op_1_bw="6" op_2_bw="1">
<![CDATA[
:26 %tmp_62_cast = bitconcatenate i7 @_ssdm_op_BitConcatenate.i7.i6.i1, i6 %trunc_ln75_1, i1 0

]]></Node>
<StgValue><ssdm name="tmp_62_cast"/></StgValue>
</operation>

<operation id="110" st_id="13" stage="1" lat="1">
<core>Adder</core>
<MemPortIdVec></MemPortIdVec>
<condition id="-1">
<or_exp><and_exp></and_exp></or_exp>
</condition>

<Node id="78" bw="7" op_0_bw="7" op_1_bw="7">
<![CDATA[
:27 %sub_ln75 = sub i7 %tmp_61_cast, i7 %tmp_62_cast

]]></Node>
<StgValue><ssdm name="sub_ln75"/></StgValue>
</operation>

<operation id="111" st_id="13" stage="2" lat="2">
<core>RAM</core>
<MemPortIdVec>0 </MemPortIdVec>
<condition id="-1">
<or_exp><and_exp></and_exp></or_exp>
</condition>

<Node id="87" bw="32" op_0_bw="7">
<![CDATA[
:36 %wp_parameters_load_14 = load i7 %wp_parameters_addr

]]></Node>
<StgValue><ssdm name="wp_parameters_load_14"/></StgValue>
</operation>
</state>

<state id="14" st_id="14">

<operation id="112" st_id="14" stage="1" lat="1">
<core>NULL</core>
<MemPortIdVec></MemPortIdVec>
<condition id="-1">
<or_exp><and_exp></and_exp></or_exp>
</condition>

<Node id="65" bw="7" op_0_bw="7" op_1_bw="7">
<![CDATA[
:14 %or_ln73 = or i7 %sub_ln73, i7 1

]]></Node>
<StgValue><ssdm name="or_ln73"/></StgValue>
</operation>

<operation id="113" st_id="14" stage="1" lat="1">
<core>NULL</core>
<MemPortIdVec></MemPortIdVec>
<condition id="-1">
<or_exp><and_exp></and_exp></or_exp>
</condition>

<Node id="66" bw="64" op_0_bw="7">
<![CDATA[
:15 %zext_ln73 = zext i7 %or_ln73

]]></Node>
<StgValue><ssdm name="zext_ln73"/></StgValue>
</operation>

<operation id="114" st_id="14" stage="1" lat="1">
<core>NULL</core>
<MemPortIdVec></MemPortIdVec>
<condition id="-1">
<or_exp><and_exp></and_exp></or_exp>
</condition>

<Node id="67" bw="7" op_0_bw="32" op_1_bw="64" op_2_bw="64">
<![CDATA[
:16 %wp_parameters_addr_31 = getelementptr i32 %wp_parameters, i64 0, i64 %zext_ln73

]]></Node>
<StgValue><ssdm name="wp_parameters_addr_31"/></StgValue>
</operation>

<operation id="115" st_id="14" stage="1" lat="1">
<core>Adder</core>
<MemPortIdVec></MemPortIdVec>
<condition id="-1">
<or_exp><and_exp></and_exp></or_exp>
</condition>

<Node id="68" bw="7" op_0_bw="7" op_1_bw="7">
<![CDATA[
:17 %add_ln74 = add i7 %sub_ln73, i7 2

]]></Node>
<StgValue><ssdm name="add_ln74"/></StgValue>
</operation>

<operation id="116" st_id="14" stage="1" lat="1">
<core>NULL</core>
<MemPortIdVec></MemPortIdVec>
<condition id="-1">
<or_exp><and_exp></and_exp></or_exp>
</condition>

<Node id="69" bw="64" op_0_bw="7">
<![CDATA[
:18 %zext_ln74 = zext i7 %add_ln74

]]></Node>
<StgValue><ssdm name="zext_ln74"/></StgValue>
</operation>

<operation id="117" st_id="14" stage="1" lat="1">
<core>NULL</core>
<MemPortIdVec></MemPortIdVec>
<condition id="-1">
<or_exp><and_exp></and_exp></or_exp>
</condition>

<Node id="70" bw="7" op_0_bw="32" op_1_bw="64" op_2_bw="64">
<![CDATA[
:19 %wp_parameters_addr_32 = getelementptr i32 %wp_parameters, i64 0, i64 %zext_ln74

]]></Node>
<StgValue><ssdm name="wp_parameters_addr_32"/></StgValue>
</operation>

<operation id="118" st_id="14" stage="1" lat="1">
<core>RAM</core>
<MemPortIdVec>0 </MemPortIdVec>
<condition id="-1">
<or_exp><and_exp></and_exp></or_exp>
</condition>

<Node id="71" bw="0" op_0_bw="32" op_1_bw="7">
<![CDATA[
:20 %store_ln73 = store i32 %b_V, i7 %wp_parameters_addr_31

]]></Node>
<StgValue><ssdm name="store_ln73"/></StgValue>
</operation>

<operation id="119" st_id="14" stage="1" lat="1">
<core>RAM</core>
<MemPortIdVec>1 </MemPortIdVec>
<condition id="-1">
<or_exp><and_exp></and_exp></or_exp>
</condition>

<Node id="72" bw="0" op_0_bw="32" op_1_bw="7">
<![CDATA[
:21 %store_ln74 = store i32 %c_V, i7 %wp_parameters_addr_32

]]></Node>
<StgValue><ssdm name="store_ln74"/></StgValue>
</operation>

<operation id="120" st_id="14" stage="1" lat="2">
<core>RAM</core>
<MemPortIdVec>0 </MemPortIdVec>
<condition id="-1">
<or_exp><and_exp></and_exp></or_exp>
</condition>

<Node id="87" bw="32" op_0_bw="7">
<![CDATA[
:36 %wp_parameters_load_14 = load i7 %wp_parameters_addr

]]></Node>
<StgValue><ssdm name="wp_parameters_load_14"/></StgValue>
</operation>

<operation id="121" st_id="14" stage="1" lat="1">
<core>NULL</core>
<MemPortIdVec></MemPortIdVec>
<condition id="-1">
<or_exp><and_exp></and_exp></or_exp>
</condition>

<Node id="88" bw="4" op_0_bw="32">
<![CDATA[
:37 %trunc_ln77 = trunc i32 %wp_parameters_load_14

]]></Node>
<StgValue><ssdm name="trunc_ln77"/></StgValue>
</operation>

<operation id="122" st_id="14" stage="1" lat="1">
<core>NULL</core>
<MemPortIdVec></MemPortIdVec>
<condition id="-1">
<or_exp><and_exp></and_exp></or_exp>
</condition>

<Node id="89" bw="7" op_0_bw="7" op_1_bw="4" op_2_bw="3">
<![CDATA[
:38 %tmp_63_cast = bitconcatenate i7 @_ssdm_op_BitConcatenate.i7.i4.i3, i4 %trunc_ln77, i3 0

]]></Node>
<StgValue><ssdm name="tmp_63_cast"/></StgValue>
</operation>

<operation id="123" st_id="14" stage="1" lat="1">
<core>NULL</core>
<MemPortIdVec></MemPortIdVec>
<condition id="-1">
<or_exp><and_exp></and_exp></or_exp>
</condition>

<Node id="90" bw="6" op_0_bw="32">
<![CDATA[
:39 %trunc_ln77_1 = trunc i32 %wp_parameters_load_14

]]></Node>
<StgValue><ssdm name="trunc_ln77_1"/></StgValue>
</operation>

<operation id="124" st_id="14" stage="1" lat="1">
<core>NULL</core>
<MemPortIdVec></MemPortIdVec>
<condition id="-1">
<or_exp><and_exp></and_exp></or_exp>
</condition>

<Node id="91" bw="7" op_0_bw="7" op_1_bw="6" op_2_bw="1">
<![CDATA[
:40 %tmp_64_cast = bitconcatenate i7 @_ssdm_op_BitConcatenate.i7.i6.i1, i6 %trunc_ln77_1, i1 0

]]></Node>
<StgValue><ssdm name="tmp_64_cast"/></StgValue>
</operation>

<operation id="125" st_id="14" stage="1" lat="1">
<core>TAddSub</core>
<MemPortIdVec></MemPortIdVec>
<condition id="-1">
<or_exp><and_exp></and_exp></or_exp>
</condition>

<Node id="92" bw="7" op_0_bw="7" op_1_bw="7">
<![CDATA[
:41 %sub_ln77 = sub i7 %tmp_63_cast, i7 %tmp_64_cast

]]></Node>
<StgValue><ssdm name="sub_ln77"/></StgValue>
</operation>

<operation id="126" st_id="14" stage="1" lat="1">
<core>TAddSub</core>
<MemPortIdVec></MemPortIdVec>
<condition id="-1">
<or_exp><and_exp></and_exp></or_exp>
</condition>

<Node id="93" bw="7" op_0_bw="7" op_1_bw="7">
<![CDATA[
:42 %add_ln77 = add i7 %sub_ln77, i7 5

]]></Node>
<StgValue><ssdm name="add_ln77"/></StgValue>
</operation>
</state>

<state id="15" st_id="15">

<operation id="127" st_id="15" stage="1" lat="1">
<core>Adder</core>
<MemPortIdVec></MemPortIdVec>
<condition id="-1">
<or_exp><and_exp></and_exp></or_exp>
</condition>

<Node id="79" bw="7" op_0_bw="7" op_1_bw="7">
<![CDATA[
:28 %add_ln75 = add i7 %sub_ln75, i7 3

]]></Node>
<StgValue><ssdm name="add_ln75"/></StgValue>
</operation>

<operation id="128" st_id="15" stage="1" lat="1">
<core>NULL</core>
<MemPortIdVec></MemPortIdVec>
<condition id="-1">
<or_exp><and_exp></and_exp></or_exp>
</condition>

<Node id="80" bw="64" op_0_bw="7">
<![CDATA[
:29 %zext_ln75 = zext i7 %add_ln75

]]></Node>
<StgValue><ssdm name="zext_ln75"/></StgValue>
</operation>

<operation id="129" st_id="15" stage="1" lat="1">
<core>NULL</core>
<MemPortIdVec></MemPortIdVec>
<condition id="-1">
<or_exp><and_exp></and_exp></or_exp>
</condition>

<Node id="81" bw="7" op_0_bw="32" op_1_bw="64" op_2_bw="64">
<![CDATA[
:30 %wp_parameters_addr_33 = getelementptr i32 %wp_parameters, i64 0, i64 %zext_ln75

]]></Node>
<StgValue><ssdm name="wp_parameters_addr_33"/></StgValue>
</operation>

<operation id="130" st_id="15" stage="1" lat="1">
<core>Adder</core>
<MemPortIdVec></MemPortIdVec>
<condition id="-1">
<or_exp><and_exp></and_exp></or_exp>
</condition>

<Node id="82" bw="7" op_0_bw="7" op_1_bw="7">
<![CDATA[
:31 %add_ln76 = add i7 %sub_ln75, i7 4

]]></Node>
<StgValue><ssdm name="add_ln76"/></StgValue>
</operation>

<operation id="131" st_id="15" stage="1" lat="1">
<core>NULL</core>
<MemPortIdVec></MemPortIdVec>
<condition id="-1">
<or_exp><and_exp></and_exp></or_exp>
</condition>

<Node id="83" bw="64" op_0_bw="7">
<![CDATA[
:32 %zext_ln76 = zext i7 %add_ln76

]]></Node>
<StgValue><ssdm name="zext_ln76"/></StgValue>
</operation>

<operation id="132" st_id="15" stage="1" lat="1">
<core>NULL</core>
<MemPortIdVec></MemPortIdVec>
<condition id="-1">
<or_exp><and_exp></and_exp></or_exp>
</condition>

<Node id="84" bw="7" op_0_bw="32" op_1_bw="64" op_2_bw="64">
<![CDATA[
:33 %wp_parameters_addr_34 = getelementptr i32 %wp_parameters, i64 0, i64 %zext_ln76

]]></Node>
<StgValue><ssdm name="wp_parameters_addr_34"/></StgValue>
</operation>

<operation id="133" st_id="15" stage="1" lat="1">
<core>RAM</core>
<MemPortIdVec>0 </MemPortIdVec>
<condition id="-1">
<or_exp><and_exp></and_exp></or_exp>
</condition>

<Node id="85" bw="0" op_0_bw="32" op_1_bw="7">
<![CDATA[
:34 %store_ln75 = store i32 %d_V, i7 %wp_parameters_addr_33

]]></Node>
<StgValue><ssdm name="store_ln75"/></StgValue>
</operation>

<operation id="134" st_id="15" stage="1" lat="1">
<core>RAM</core>
<MemPortIdVec>1 </MemPortIdVec>
<condition id="-1">
<or_exp><and_exp></and_exp></or_exp>
</condition>

<Node id="86" bw="0" op_0_bw="32" op_1_bw="7">
<![CDATA[
:35 %store_ln76 = store i32 %sext_ln43, i7 %wp_parameters_addr_34

]]></Node>
<StgValue><ssdm name="store_ln76"/></StgValue>
</operation>
</state>

<state id="16" st_id="16">

<operation id="135" st_id="16" stage="1" lat="1">
<core>NULL</core>
<MemPortIdVec></MemPortIdVec>
<condition id="-1">
<or_exp><and_exp><literal name="icmp_ln70" val="1"/>
</and_exp></or_exp>
</condition>

<Node id="94" bw="64" op_0_bw="7">
<![CDATA[
:43 %zext_ln77 = zext i7 %add_ln77

]]></Node>
<StgValue><ssdm name="zext_ln77"/></StgValue>
</operation>

<operation id="136" st_id="16" stage="1" lat="1">
<core>NULL</core>
<MemPortIdVec></MemPortIdVec>
<condition id="-1">
<or_exp><and_exp><literal name="icmp_ln70" val="1"/>
</and_exp></or_exp>
</condition>

<Node id="95" bw="7" op_0_bw="32" op_1_bw="64" op_2_bw="64">
<![CDATA[
:44 %wp_parameters_addr_35 = getelementptr i32 %wp_parameters, i64 0, i64 %zext_ln77

]]></Node>
<StgValue><ssdm name="wp_parameters_addr_35"/></StgValue>
</operation>

<operation id="137" st_id="16" stage="1" lat="1">
<core>RAM</core>
<MemPortIdVec>0 </MemPortIdVec>
<condition id="-1">
<or_exp><and_exp><literal name="icmp_ln70" val="1"/>
</and_exp></or_exp>
</condition>

<Node id="96" bw="0" op_0_bw="32" op_1_bw="7">
<![CDATA[
:45 %store_ln77 = store i32 %sext_ln46, i7 %wp_parameters_addr_35

]]></Node>
<StgValue><ssdm name="store_ln77"/></StgValue>
</operation>

<operation id="138" st_id="16" stage="1" lat="1">
<core>Adder</core>
<MemPortIdVec></MemPortIdVec>
<condition id="-1">
<or_exp><and_exp><literal name="icmp_ln70" val="1"/>
</and_exp></or_exp>
</condition>

<Node id="97" bw="32" op_0_bw="32" op_1_bw="32">
<![CDATA[
:46 %add_ln691 = add i32 %wp_parameters_load_14, i32 1

]]></Node>
<StgValue><ssdm name="add_ln691"/></StgValue>
</operation>

<operation id="139" st_id="16" stage="1" lat="1">
<core>RAM</core>
<MemPortIdVec>1 </MemPortIdVec>
<condition id="-1">
<or_exp><and_exp><literal name="icmp_ln70" val="1"/>
</and_exp></or_exp>
</condition>

<Node id="98" bw="0" op_0_bw="32" op_1_bw="7" op_2_bw="0" op_3_bw="0" op_4_bw="0">
<![CDATA[
:47 %store_ln691 = store i32 %add_ln691, i7 %wp_parameters_addr

]]></Node>
<StgValue><ssdm name="store_ln691"/></StgValue>
</operation>

<operation id="140" st_id="16" stage="1" lat="1">
<core>NULL</core>
<MemPortIdVec></MemPortIdVec>
<condition id="-1">
<or_exp><and_exp><literal name="icmp_ln70" val="1"/>
</and_exp></or_exp>
</condition>

<Node id="99" bw="0" op_0_bw="32" op_1_bw="32" op_2_bw="0" op_3_bw="0">
<![CDATA[
:48 %store_ln80 = store i32 %add_ln691, i32 %empty

]]></Node>
<StgValue><ssdm name="store_ln80"/></StgValue>
</operation>

<operation id="141" st_id="16" stage="1" lat="1">
<core>NULL</core>
<MemPortIdVec></MemPortIdVec>
<condition id="-1">
<or_exp><and_exp><literal name="icmp_ln70" val="1"/>
</and_exp></or_exp>
</condition>

<Node id="100" bw="0" op_0_bw="0">
<![CDATA[
:49 %br_ln80 = br void %.split._crit_edge

]]></Node>
<StgValue><ssdm name="br_ln80"/></StgValue>
</operation>

<operation id="142" st_id="16" stage="1" lat="1">
<core>NULL</core>
<MemPortIdVec></MemPortIdVec>
<condition id="-1">
<or_exp><and_exp></and_exp></or_exp>
</condition>

<Node id="102" bw="0" op_0_bw="0">
<![CDATA[
.split._crit_edge:0 %br_ln0 = br void

]]></Node>
<StgValue><ssdm name="br_ln0"/></StgValue>
</operation>
</state>
</state_list>


<ports>
<port id="162" name="wp_superpoints" dir="0" iftype="1">
<core>RAM</core><StgValue><ssdm name="wp_superpoints"/><MemPortTyVec>1 1 </MemPortTyVec>
</StgValue>
</port>
<port id="163" name="wp_parameters" dir="2" iftype="1">
<core>RAM</core><StgValue><ssdm name="wp_parameters"/><MemPortTyVec>2 2 </MemPortTyVec>
</StgValue>
</port>
<port id="164" name="radiiDivisionList" dir="0" iftype="1">
<core>ROM</core><StgValue><ssdm name="radiiDivisionList"/><MemPortTyVec>1 </MemPortTyVec>
</StgValue>
</port>
</ports>


<dataflows>
<dataflow id="166" from="StgValue_165" to="empty" fromId="165" toId="17">
</dataflow>
<dataflow id="167" from="wp_superpoints" to="wp_superpoints_addr" fromId="162" toId="18">
</dataflow>
<dataflow id="169" from="StgValue_168" to="wp_superpoints_addr" fromId="168" toId="18">
</dataflow>
<dataflow id="171" from="StgValue_170" to="wp_superpoints_addr" fromId="170" toId="18">
</dataflow>
<dataflow id="172" from="wp_superpoints" to="wp_superpoints_addr_2" fromId="162" toId="19">
</dataflow>
<dataflow id="173" from="StgValue_168" to="wp_superpoints_addr_2" fromId="168" toId="19">
</dataflow>
<dataflow id="175" from="StgValue_174" to="wp_superpoints_addr_2" fromId="174" toId="19">
</dataflow>
<dataflow id="176" from="wp_superpoints_addr" to="wp_superpoints_load" fromId="18" toId="20">
</dataflow>
<dataflow id="177" from="wp_superpoints_addr_2" to="wp_superpoints_load_1" fromId="19" toId="21">
</dataflow>
<dataflow id="179" from="StgValue_178" to="store_ln59" fromId="178" toId="22">
</dataflow>
<dataflow id="180" from="empty" to="store_ln59" fromId="17" toId="22">
</dataflow>
<dataflow id="181" from="wp_superpoints_addr" to="wp_superpoints_load" fromId="18" toId="23">
</dataflow>
<dataflow id="182" from="wp_superpoints_load" to="icmp_ln878" fromId="23" toId="24">
</dataflow>
<dataflow id="184" from="StgValue_183" to="icmp_ln878" fromId="183" toId="24">
</dataflow>
<dataflow id="185" from="wp_superpoints_addr_2" to="wp_superpoints_load_1" fromId="19" toId="25">
</dataflow>
<dataflow id="186" from="wp_superpoints_load_1" to="icmp_ln878_14" fromId="25" toId="26">
</dataflow>
<dataflow id="188" from="StgValue_187" to="icmp_ln878_14" fromId="187" toId="26">
</dataflow>
<dataflow id="189" from="wp_parameters" to="wp_parameters_addr" fromId="163" toId="27">
</dataflow>
<dataflow id="190" from="StgValue_168" to="wp_parameters_addr" fromId="168" toId="27">
</dataflow>
<dataflow id="192" from="StgValue_191" to="wp_parameters_addr" fromId="191" toId="27">
</dataflow>
<dataflow id="193" from="icmp_ln878" to="z1_min_V" fromId="24" toId="28">
</dataflow>
<dataflow id="194" from="StgValue_183" to="z1_min_V" fromId="183" toId="28">
</dataflow>
<dataflow id="195" from="wp_superpoints_load" to="z1_min_V" fromId="23" toId="28">
</dataflow>
<dataflow id="196" from="z1_min_V" to="trunc_ln43" fromId="28" toId="29">
</dataflow>
<dataflow id="197" from="icmp_ln878_14" to="z1_max_V" fromId="26" toId="30">
</dataflow>
<dataflow id="198" from="wp_superpoints_load_1" to="z1_max_V" fromId="25" toId="30">
</dataflow>
<dataflow id="199" from="StgValue_187" to="z1_max_V" fromId="187" toId="30">
</dataflow>
<dataflow id="200" from="z1_max_V" to="trunc_ln44" fromId="30" toId="31">
</dataflow>
<dataflow id="201" from="z1_min_V" to="icmp_ln886" fromId="28" toId="32">
</dataflow>
<dataflow id="202" from="z1_max_V" to="icmp_ln886" fromId="30" toId="32">
</dataflow>
<dataflow id="203" from="icmp_ln886" to="z1_max_V_1" fromId="32" toId="33">
</dataflow>
<dataflow id="205" from="StgValue_204" to="z1_max_V_1" fromId="204" toId="33">
</dataflow>
<dataflow id="206" from="trunc_ln44" to="z1_max_V_1" fromId="31" toId="33">
</dataflow>
<dataflow id="207" from="z1_max_V_1" to="sext_ln46" fromId="33" toId="34">
</dataflow>
<dataflow id="208" from="icmp_ln886" to="z1_min_V_1" fromId="32" toId="35">
</dataflow>
<dataflow id="209" from="StgValue_204" to="z1_min_V_1" fromId="204" toId="35">
</dataflow>
<dataflow id="210" from="trunc_ln43" to="z1_min_V_1" fromId="29" toId="35">
</dataflow>
<dataflow id="211" from="z1_min_V_1" to="sext_ln43" fromId="35" toId="36">
</dataflow>
<dataflow id="212" from="StgValue_178" to="store_ln57" fromId="178" toId="37">
</dataflow>
<dataflow id="213" from="wp_parameters_addr" to="store_ln57" fromId="27" toId="37">
</dataflow>
<dataflow id="215" from="StgValue_214" to="i" fromId="214" toId="39">
<condition id="-1">
<or_exp><and_exp></and_exp></or_exp>
</condition>
</dataflow>
<dataflow id="216" from="br_ln59" to="i" fromId="38" toId="39">
</dataflow>
<dataflow id="217" from="add_ln64" to="i" fromId="53" toId="39">
<BackEdge/>
<condition id="-1">
<or_exp><and_exp></and_exp></or_exp>
</condition>
</dataflow>
<dataflow id="218" from="br_ln0" to="i" fromId="142" toId="39">
<BackEdge/>
</dataflow>
<dataflow id="220" from="_ssdm_op_BitConcatenate.i8.i3.i5" to="tmp" fromId="219" toId="40">
</dataflow>
<dataflow id="221" from="i" to="tmp" fromId="39" toId="40">
</dataflow>
<dataflow id="223" from="StgValue_222" to="tmp" fromId="222" toId="40">
</dataflow>
<dataflow id="224" from="tmp" to="or_ln61" fromId="40" toId="41">
</dataflow>
<dataflow id="226" from="StgValue_225" to="or_ln61" fromId="225" toId="41">
</dataflow>
<dataflow id="228" from="_ssdm_op_BitConcatenate.i64.i56.i8" to="tmp_s" fromId="227" toId="42">
</dataflow>
<dataflow id="230" from="StgValue_229" to="tmp_s" fromId="229" toId="42">
</dataflow>
<dataflow id="231" from="or_ln61" to="tmp_s" fromId="41" toId="42">
</dataflow>
<dataflow id="232" from="wp_superpoints" to="wp_superpoints_addr_3" fromId="162" toId="43">
</dataflow>
<dataflow id="233" from="StgValue_168" to="wp_superpoints_addr_3" fromId="168" toId="43">
</dataflow>
<dataflow id="234" from="tmp_s" to="wp_superpoints_addr_3" fromId="42" toId="43">
</dataflow>
<dataflow id="235" from="tmp" to="or_ln62" fromId="40" toId="44">
</dataflow>
<dataflow id="237" from="StgValue_236" to="or_ln62" fromId="236" toId="44">
</dataflow>
<dataflow id="238" from="_ssdm_op_BitConcatenate.i64.i56.i8" to="tmp_24" fromId="227" toId="45">
</dataflow>
<dataflow id="239" from="StgValue_229" to="tmp_24" fromId="229" toId="45">
</dataflow>
<dataflow id="240" from="or_ln62" to="tmp_24" fromId="44" toId="45">
</dataflow>
<dataflow id="241" from="wp_superpoints" to="wp_superpoints_addr_4" fromId="162" toId="46">
</dataflow>
<dataflow id="242" from="StgValue_168" to="wp_superpoints_addr_4" fromId="168" toId="46">
</dataflow>
<dataflow id="243" from="tmp_24" to="wp_superpoints_addr_4" fromId="45" toId="46">
</dataflow>
<dataflow id="244" from="i" to="icmp_ln59" fromId="39" toId="47">
</dataflow>
<dataflow id="246" from="StgValue_245" to="icmp_ln59" fromId="245" toId="47">
</dataflow>
<dataflow id="248" from="_ssdm_op_SpecLoopTripCount" to="empty_80" fromId="247" toId="48">
</dataflow>
<dataflow id="250" from="StgValue_249" to="empty_80" fromId="249" toId="48">
</dataflow>
<dataflow id="251" from="StgValue_249" to="empty_80" fromId="249" toId="48">
</dataflow>
<dataflow id="252" from="StgValue_249" to="empty_80" fromId="249" toId="48">
</dataflow>
<dataflow id="253" from="icmp_ln59" to="br_ln59" fromId="47" toId="49">
</dataflow>
<dataflow id="254" from="wp_superpoints_addr_3" to="wp_superpoints_load_2" fromId="43" toId="50">
</dataflow>
<dataflow id="255" from="wp_superpoints_addr_4" to="wp_superpoints_load_3" fromId="46" toId="51">
</dataflow>
<dataflow id="256" from="i" to="add_ln64" fromId="39" toId="53">
</dataflow>
<dataflow id="257" from="StgValue_214" to="add_ln64" fromId="214" toId="53">
</dataflow>
<dataflow id="258" from="wp_superpoints_addr_3" to="wp_superpoints_load_2" fromId="43" toId="54">
</dataflow>
<dataflow id="259" from="wp_superpoints_addr_4" to="wp_superpoints_load_3" fromId="46" toId="55">
</dataflow>
<dataflow id="261" from="straightLineProjectorFromLayerIJtoK" to="a_V" fromId="260" toId="56">
</dataflow>
<dataflow id="262" from="sext_ln43" to="a_V" fromId="36" toId="56">
</dataflow>
<dataflow id="263" from="wp_superpoints_load_3" to="a_V" fromId="55" toId="56">
</dataflow>
<dataflow id="264" from="StgValue_214" to="a_V" fromId="214" toId="56">
</dataflow>
<dataflow id="265" from="add_ln64" to="a_V" fromId="53" toId="56">
</dataflow>
<dataflow id="266" from="StgValue_245" to="a_V" fromId="245" toId="56">
</dataflow>
<dataflow id="267" from="radiiDivisionList" to="a_V" fromId="164" toId="56">
</dataflow>
<dataflow id="268" from="straightLineProjectorFromLayerIJtoK" to="b_V" fromId="260" toId="57">
</dataflow>
<dataflow id="269" from="sext_ln46" to="b_V" fromId="34" toId="57">
</dataflow>
<dataflow id="270" from="wp_superpoints_load_3" to="b_V" fromId="55" toId="57">
</dataflow>
<dataflow id="271" from="StgValue_214" to="b_V" fromId="214" toId="57">
</dataflow>
<dataflow id="272" from="add_ln64" to="b_V" fromId="53" toId="57">
</dataflow>
<dataflow id="273" from="StgValue_245" to="b_V" fromId="245" toId="57">
</dataflow>
<dataflow id="274" from="radiiDivisionList" to="b_V" fromId="164" toId="57">
</dataflow>
<dataflow id="275" from="straightLineProjectorFromLayerIJtoK" to="c_V" fromId="260" toId="58">
</dataflow>
<dataflow id="276" from="sext_ln43" to="c_V" fromId="36" toId="58">
</dataflow>
<dataflow id="277" from="wp_superpoints_load_2" to="c_V" fromId="54" toId="58">
</dataflow>
<dataflow id="278" from="StgValue_214" to="c_V" fromId="214" toId="58">
</dataflow>
<dataflow id="279" from="add_ln64" to="c_V" fromId="53" toId="58">
</dataflow>
<dataflow id="280" from="StgValue_245" to="c_V" fromId="245" toId="58">
</dataflow>
<dataflow id="281" from="radiiDivisionList" to="c_V" fromId="164" toId="58">
</dataflow>
<dataflow id="282" from="straightLineProjectorFromLayerIJtoK" to="d_V" fromId="260" toId="59">
</dataflow>
<dataflow id="283" from="sext_ln46" to="d_V" fromId="34" toId="59">
</dataflow>
<dataflow id="284" from="wp_superpoints_load_2" to="d_V" fromId="54" toId="59">
</dataflow>
<dataflow id="285" from="StgValue_214" to="d_V" fromId="214" toId="59">
</dataflow>
<dataflow id="286" from="add_ln64" to="d_V" fromId="53" toId="59">
</dataflow>
<dataflow id="287" from="StgValue_245" to="d_V" fromId="245" toId="59">
</dataflow>
<dataflow id="288" from="radiiDivisionList" to="d_V" fromId="164" toId="59">
</dataflow>
<dataflow id="289" from="straightLineProjectorFromLayerIJtoK" to="a_V" fromId="260" toId="60">
</dataflow>
<dataflow id="290" from="sext_ln43" to="a_V" fromId="36" toId="60">
</dataflow>
<dataflow id="291" from="wp_superpoints_load_3" to="a_V" fromId="55" toId="60">
</dataflow>
<dataflow id="292" from="StgValue_214" to="a_V" fromId="214" toId="60">
</dataflow>
<dataflow id="293" from="add_ln64" to="a_V" fromId="53" toId="60">
</dataflow>
<dataflow id="294" from="StgValue_245" to="a_V" fromId="245" toId="60">
</dataflow>
<dataflow id="295" from="radiiDivisionList" to="a_V" fromId="164" toId="60">
</dataflow>
<dataflow id="296" from="straightLineProjectorFromLayerIJtoK" to="b_V" fromId="260" toId="61">
</dataflow>
<dataflow id="297" from="sext_ln46" to="b_V" fromId="34" toId="61">
</dataflow>
<dataflow id="298" from="wp_superpoints_load_3" to="b_V" fromId="55" toId="61">
</dataflow>
<dataflow id="299" from="StgValue_214" to="b_V" fromId="214" toId="61">
</dataflow>
<dataflow id="300" from="add_ln64" to="b_V" fromId="53" toId="61">
</dataflow>
<dataflow id="301" from="StgValue_245" to="b_V" fromId="245" toId="61">
</dataflow>
<dataflow id="302" from="radiiDivisionList" to="b_V" fromId="164" toId="61">
</dataflow>
<dataflow id="303" from="straightLineProjectorFromLayerIJtoK" to="c_V" fromId="260" toId="62">
</dataflow>
<dataflow id="304" from="sext_ln43" to="c_V" fromId="36" toId="62">
</dataflow>
<dataflow id="305" from="wp_superpoints_load_2" to="c_V" fromId="54" toId="62">
</dataflow>
<dataflow id="306" from="StgValue_214" to="c_V" fromId="214" toId="62">
</dataflow>
<dataflow id="307" from="add_ln64" to="c_V" fromId="53" toId="62">
</dataflow>
<dataflow id="308" from="StgValue_245" to="c_V" fromId="245" toId="62">
</dataflow>
<dataflow id="309" from="radiiDivisionList" to="c_V" fromId="164" toId="62">
</dataflow>
<dataflow id="310" from="straightLineProjectorFromLayerIJtoK" to="d_V" fromId="260" toId="63">
</dataflow>
<dataflow id="311" from="sext_ln46" to="d_V" fromId="34" toId="63">
</dataflow>
<dataflow id="312" from="wp_superpoints_load_2" to="d_V" fromId="54" toId="63">
</dataflow>
<dataflow id="313" from="StgValue_214" to="d_V" fromId="214" toId="63">
</dataflow>
<dataflow id="314" from="add_ln64" to="d_V" fromId="53" toId="63">
</dataflow>
<dataflow id="315" from="StgValue_245" to="d_V" fromId="245" toId="63">
</dataflow>
<dataflow id="316" from="radiiDivisionList" to="d_V" fromId="164" toId="63">
</dataflow>
<dataflow id="317" from="straightLineProjectorFromLayerIJtoK" to="a_V" fromId="260" toId="64">
</dataflow>
<dataflow id="318" from="sext_ln43" to="a_V" fromId="36" toId="64">
</dataflow>
<dataflow id="319" from="wp_superpoints_load_3" to="a_V" fromId="55" toId="64">
</dataflow>
<dataflow id="320" from="StgValue_214" to="a_V" fromId="214" toId="64">
</dataflow>
<dataflow id="321" from="add_ln64" to="a_V" fromId="53" toId="64">
</dataflow>
<dataflow id="322" from="StgValue_245" to="a_V" fromId="245" toId="64">
</dataflow>
<dataflow id="323" from="radiiDivisionList" to="a_V" fromId="164" toId="64">
</dataflow>
<dataflow id="324" from="straightLineProjectorFromLayerIJtoK" to="b_V" fromId="260" toId="65">
</dataflow>
<dataflow id="325" from="sext_ln46" to="b_V" fromId="34" toId="65">
</dataflow>
<dataflow id="326" from="wp_superpoints_load_3" to="b_V" fromId="55" toId="65">
</dataflow>
<dataflow id="327" from="StgValue_214" to="b_V" fromId="214" toId="65">
</dataflow>
<dataflow id="328" from="add_ln64" to="b_V" fromId="53" toId="65">
</dataflow>
<dataflow id="329" from="StgValue_245" to="b_V" fromId="245" toId="65">
</dataflow>
<dataflow id="330" from="radiiDivisionList" to="b_V" fromId="164" toId="65">
</dataflow>
<dataflow id="331" from="straightLineProjectorFromLayerIJtoK" to="c_V" fromId="260" toId="66">
</dataflow>
<dataflow id="332" from="sext_ln43" to="c_V" fromId="36" toId="66">
</dataflow>
<dataflow id="333" from="wp_superpoints_load_2" to="c_V" fromId="54" toId="66">
</dataflow>
<dataflow id="334" from="StgValue_214" to="c_V" fromId="214" toId="66">
</dataflow>
<dataflow id="335" from="add_ln64" to="c_V" fromId="53" toId="66">
</dataflow>
<dataflow id="336" from="StgValue_245" to="c_V" fromId="245" toId="66">
</dataflow>
<dataflow id="337" from="radiiDivisionList" to="c_V" fromId="164" toId="66">
</dataflow>
<dataflow id="338" from="straightLineProjectorFromLayerIJtoK" to="d_V" fromId="260" toId="67">
</dataflow>
<dataflow id="339" from="sext_ln46" to="d_V" fromId="34" toId="67">
</dataflow>
<dataflow id="340" from="wp_superpoints_load_2" to="d_V" fromId="54" toId="67">
</dataflow>
<dataflow id="341" from="StgValue_214" to="d_V" fromId="214" toId="67">
</dataflow>
<dataflow id="342" from="add_ln64" to="d_V" fromId="53" toId="67">
</dataflow>
<dataflow id="343" from="StgValue_245" to="d_V" fromId="245" toId="67">
</dataflow>
<dataflow id="344" from="radiiDivisionList" to="d_V" fromId="164" toId="67">
</dataflow>
<dataflow id="345" from="straightLineProjectorFromLayerIJtoK" to="a_V" fromId="260" toId="68">
</dataflow>
<dataflow id="346" from="sext_ln43" to="a_V" fromId="36" toId="68">
</dataflow>
<dataflow id="347" from="wp_superpoints_load_3" to="a_V" fromId="55" toId="68">
</dataflow>
<dataflow id="348" from="StgValue_214" to="a_V" fromId="214" toId="68">
</dataflow>
<dataflow id="349" from="add_ln64" to="a_V" fromId="53" toId="68">
</dataflow>
<dataflow id="350" from="StgValue_245" to="a_V" fromId="245" toId="68">
</dataflow>
<dataflow id="351" from="radiiDivisionList" to="a_V" fromId="164" toId="68">
</dataflow>
<dataflow id="352" from="straightLineProjectorFromLayerIJtoK" to="b_V" fromId="260" toId="69">
</dataflow>
<dataflow id="353" from="sext_ln46" to="b_V" fromId="34" toId="69">
</dataflow>
<dataflow id="354" from="wp_superpoints_load_3" to="b_V" fromId="55" toId="69">
</dataflow>
<dataflow id="355" from="StgValue_214" to="b_V" fromId="214" toId="69">
</dataflow>
<dataflow id="356" from="add_ln64" to="b_V" fromId="53" toId="69">
</dataflow>
<dataflow id="357" from="StgValue_245" to="b_V" fromId="245" toId="69">
</dataflow>
<dataflow id="358" from="radiiDivisionList" to="b_V" fromId="164" toId="69">
</dataflow>
<dataflow id="359" from="straightLineProjectorFromLayerIJtoK" to="c_V" fromId="260" toId="70">
</dataflow>
<dataflow id="360" from="sext_ln43" to="c_V" fromId="36" toId="70">
</dataflow>
<dataflow id="361" from="wp_superpoints_load_2" to="c_V" fromId="54" toId="70">
</dataflow>
<dataflow id="362" from="StgValue_214" to="c_V" fromId="214" toId="70">
</dataflow>
<dataflow id="363" from="add_ln64" to="c_V" fromId="53" toId="70">
</dataflow>
<dataflow id="364" from="StgValue_245" to="c_V" fromId="245" toId="70">
</dataflow>
<dataflow id="365" from="radiiDivisionList" to="c_V" fromId="164" toId="70">
</dataflow>
<dataflow id="366" from="straightLineProjectorFromLayerIJtoK" to="d_V" fromId="260" toId="71">
</dataflow>
<dataflow id="367" from="sext_ln46" to="d_V" fromId="34" toId="71">
</dataflow>
<dataflow id="368" from="wp_superpoints_load_2" to="d_V" fromId="54" toId="71">
</dataflow>
<dataflow id="369" from="StgValue_214" to="d_V" fromId="214" toId="71">
</dataflow>
<dataflow id="370" from="add_ln64" to="d_V" fromId="53" toId="71">
</dataflow>
<dataflow id="371" from="StgValue_245" to="d_V" fromId="245" toId="71">
</dataflow>
<dataflow id="372" from="radiiDivisionList" to="d_V" fromId="164" toId="71">
</dataflow>
<dataflow id="373" from="straightLineProjectorFromLayerIJtoK" to="a_V" fromId="260" toId="72">
</dataflow>
<dataflow id="374" from="sext_ln43" to="a_V" fromId="36" toId="72">
</dataflow>
<dataflow id="375" from="wp_superpoints_load_3" to="a_V" fromId="55" toId="72">
</dataflow>
<dataflow id="376" from="StgValue_214" to="a_V" fromId="214" toId="72">
</dataflow>
<dataflow id="377" from="add_ln64" to="a_V" fromId="53" toId="72">
</dataflow>
<dataflow id="378" from="StgValue_245" to="a_V" fromId="245" toId="72">
</dataflow>
<dataflow id="379" from="radiiDivisionList" to="a_V" fromId="164" toId="72">
</dataflow>
<dataflow id="380" from="straightLineProjectorFromLayerIJtoK" to="b_V" fromId="260" toId="73">
</dataflow>
<dataflow id="381" from="sext_ln46" to="b_V" fromId="34" toId="73">
</dataflow>
<dataflow id="382" from="wp_superpoints_load_3" to="b_V" fromId="55" toId="73">
</dataflow>
<dataflow id="383" from="StgValue_214" to="b_V" fromId="214" toId="73">
</dataflow>
<dataflow id="384" from="add_ln64" to="b_V" fromId="53" toId="73">
</dataflow>
<dataflow id="385" from="StgValue_245" to="b_V" fromId="245" toId="73">
</dataflow>
<dataflow id="386" from="radiiDivisionList" to="b_V" fromId="164" toId="73">
</dataflow>
<dataflow id="387" from="straightLineProjectorFromLayerIJtoK" to="c_V" fromId="260" toId="74">
</dataflow>
<dataflow id="388" from="sext_ln43" to="c_V" fromId="36" toId="74">
</dataflow>
<dataflow id="389" from="wp_superpoints_load_2" to="c_V" fromId="54" toId="74">
</dataflow>
<dataflow id="390" from="StgValue_214" to="c_V" fromId="214" toId="74">
</dataflow>
<dataflow id="391" from="add_ln64" to="c_V" fromId="53" toId="74">
</dataflow>
<dataflow id="392" from="StgValue_245" to="c_V" fromId="245" toId="74">
</dataflow>
<dataflow id="393" from="radiiDivisionList" to="c_V" fromId="164" toId="74">
</dataflow>
<dataflow id="394" from="straightLineProjectorFromLayerIJtoK" to="d_V" fromId="260" toId="75">
</dataflow>
<dataflow id="395" from="sext_ln46" to="d_V" fromId="34" toId="75">
</dataflow>
<dataflow id="396" from="wp_superpoints_load_2" to="d_V" fromId="54" toId="75">
</dataflow>
<dataflow id="397" from="StgValue_214" to="d_V" fromId="214" toId="75">
</dataflow>
<dataflow id="398" from="add_ln64" to="d_V" fromId="53" toId="75">
</dataflow>
<dataflow id="399" from="StgValue_245" to="d_V" fromId="245" toId="75">
</dataflow>
<dataflow id="400" from="radiiDivisionList" to="d_V" fromId="164" toId="75">
</dataflow>
<dataflow id="401" from="straightLineProjectorFromLayerIJtoK" to="a_V" fromId="260" toId="76">
</dataflow>
<dataflow id="402" from="sext_ln43" to="a_V" fromId="36" toId="76">
</dataflow>
<dataflow id="403" from="wp_superpoints_load_3" to="a_V" fromId="55" toId="76">
</dataflow>
<dataflow id="404" from="StgValue_214" to="a_V" fromId="214" toId="76">
</dataflow>
<dataflow id="405" from="add_ln64" to="a_V" fromId="53" toId="76">
</dataflow>
<dataflow id="406" from="StgValue_245" to="a_V" fromId="245" toId="76">
</dataflow>
<dataflow id="407" from="radiiDivisionList" to="a_V" fromId="164" toId="76">
</dataflow>
<dataflow id="408" from="straightLineProjectorFromLayerIJtoK" to="b_V" fromId="260" toId="77">
</dataflow>
<dataflow id="409" from="sext_ln46" to="b_V" fromId="34" toId="77">
</dataflow>
<dataflow id="410" from="wp_superpoints_load_3" to="b_V" fromId="55" toId="77">
</dataflow>
<dataflow id="411" from="StgValue_214" to="b_V" fromId="214" toId="77">
</dataflow>
<dataflow id="412" from="add_ln64" to="b_V" fromId="53" toId="77">
</dataflow>
<dataflow id="413" from="StgValue_245" to="b_V" fromId="245" toId="77">
</dataflow>
<dataflow id="414" from="radiiDivisionList" to="b_V" fromId="164" toId="77">
</dataflow>
<dataflow id="415" from="straightLineProjectorFromLayerIJtoK" to="c_V" fromId="260" toId="78">
</dataflow>
<dataflow id="416" from="sext_ln43" to="c_V" fromId="36" toId="78">
</dataflow>
<dataflow id="417" from="wp_superpoints_load_2" to="c_V" fromId="54" toId="78">
</dataflow>
<dataflow id="418" from="StgValue_214" to="c_V" fromId="214" toId="78">
</dataflow>
<dataflow id="419" from="add_ln64" to="c_V" fromId="53" toId="78">
</dataflow>
<dataflow id="420" from="StgValue_245" to="c_V" fromId="245" toId="78">
</dataflow>
<dataflow id="421" from="radiiDivisionList" to="c_V" fromId="164" toId="78">
</dataflow>
<dataflow id="422" from="straightLineProjectorFromLayerIJtoK" to="d_V" fromId="260" toId="79">
</dataflow>
<dataflow id="423" from="sext_ln46" to="d_V" fromId="34" toId="79">
</dataflow>
<dataflow id="424" from="wp_superpoints_load_2" to="d_V" fromId="54" toId="79">
</dataflow>
<dataflow id="425" from="StgValue_214" to="d_V" fromId="214" toId="79">
</dataflow>
<dataflow id="426" from="add_ln64" to="d_V" fromId="53" toId="79">
</dataflow>
<dataflow id="427" from="StgValue_245" to="d_V" fromId="245" toId="79">
</dataflow>
<dataflow id="428" from="radiiDivisionList" to="d_V" fromId="164" toId="79">
</dataflow>
<dataflow id="429" from="empty" to="p_load84" fromId="17" toId="80">
</dataflow>
<dataflow id="431" from="_ssdm_op_SpecLoopName" to="specloopname_ln59" fromId="430" toId="81">
</dataflow>
<dataflow id="433" from="empty_11" to="specloopname_ln59" fromId="432" toId="81">
</dataflow>
<dataflow id="434" from="straightLineProjectorFromLayerIJtoK" to="a_V" fromId="260" toId="82">
</dataflow>
<dataflow id="435" from="sext_ln43" to="a_V" fromId="36" toId="82">
</dataflow>
<dataflow id="436" from="wp_superpoints_load_3" to="a_V" fromId="55" toId="82">
</dataflow>
<dataflow id="437" from="StgValue_214" to="a_V" fromId="214" toId="82">
</dataflow>
<dataflow id="438" from="add_ln64" to="a_V" fromId="53" toId="82">
</dataflow>
<dataflow id="439" from="StgValue_245" to="a_V" fromId="245" toId="82">
</dataflow>
<dataflow id="440" from="radiiDivisionList" to="a_V" fromId="164" toId="82">
</dataflow>
<dataflow id="441" from="straightLineProjectorFromLayerIJtoK" to="b_V" fromId="260" toId="83">
</dataflow>
<dataflow id="442" from="sext_ln46" to="b_V" fromId="34" toId="83">
</dataflow>
<dataflow id="443" from="wp_superpoints_load_3" to="b_V" fromId="55" toId="83">
</dataflow>
<dataflow id="444" from="StgValue_214" to="b_V" fromId="214" toId="83">
</dataflow>
<dataflow id="445" from="add_ln64" to="b_V" fromId="53" toId="83">
</dataflow>
<dataflow id="446" from="StgValue_245" to="b_V" fromId="245" toId="83">
</dataflow>
<dataflow id="447" from="radiiDivisionList" to="b_V" fromId="164" toId="83">
</dataflow>
<dataflow id="448" from="straightLineProjectorFromLayerIJtoK" to="c_V" fromId="260" toId="84">
</dataflow>
<dataflow id="449" from="sext_ln43" to="c_V" fromId="36" toId="84">
</dataflow>
<dataflow id="450" from="wp_superpoints_load_2" to="c_V" fromId="54" toId="84">
</dataflow>
<dataflow id="451" from="StgValue_214" to="c_V" fromId="214" toId="84">
</dataflow>
<dataflow id="452" from="add_ln64" to="c_V" fromId="53" toId="84">
</dataflow>
<dataflow id="453" from="StgValue_245" to="c_V" fromId="245" toId="84">
</dataflow>
<dataflow id="454" from="radiiDivisionList" to="c_V" fromId="164" toId="84">
</dataflow>
<dataflow id="455" from="straightLineProjectorFromLayerIJtoK" to="d_V" fromId="260" toId="85">
</dataflow>
<dataflow id="456" from="sext_ln46" to="d_V" fromId="34" toId="85">
</dataflow>
<dataflow id="457" from="wp_superpoints_load_2" to="d_V" fromId="54" toId="85">
</dataflow>
<dataflow id="458" from="StgValue_214" to="d_V" fromId="214" toId="85">
</dataflow>
<dataflow id="459" from="add_ln64" to="d_V" fromId="53" toId="85">
</dataflow>
<dataflow id="460" from="StgValue_245" to="d_V" fromId="245" toId="85">
</dataflow>
<dataflow id="461" from="radiiDivisionList" to="d_V" fromId="164" toId="85">
</dataflow>
<dataflow id="463" from="_ssdm_op_PartSelect.i30.i32.i32.i32" to="tmp_28" fromId="462" toId="86">
</dataflow>
<dataflow id="464" from="p_load84" to="tmp_28" fromId="80" toId="86">
</dataflow>
<dataflow id="466" from="StgValue_465" to="tmp_28" fromId="465" toId="86">
</dataflow>
<dataflow id="468" from="StgValue_467" to="tmp_28" fromId="467" toId="86">
</dataflow>
<dataflow id="469" from="tmp_28" to="icmp_ln70" fromId="86" toId="87">
</dataflow>
<dataflow id="471" from="StgValue_470" to="icmp_ln70" fromId="470" toId="87">
</dataflow>
<dataflow id="472" from="icmp_ln70" to="br_ln70" fromId="87" toId="88">
</dataflow>
<dataflow id="473" from="p_load84" to="trunc_ln72" fromId="80" toId="89">
</dataflow>
<dataflow id="475" from="_ssdm_op_BitConcatenate.i7.i4.i3" to="tmp_57_cast" fromId="474" toId="90">
</dataflow>
<dataflow id="476" from="trunc_ln72" to="tmp_57_cast" fromId="89" toId="90">
</dataflow>
<dataflow id="478" from="StgValue_477" to="tmp_57_cast" fromId="477" toId="90">
</dataflow>
<dataflow id="479" from="p_load84" to="trunc_ln72_1" fromId="80" toId="91">
</dataflow>
<dataflow id="481" from="_ssdm_op_BitConcatenate.i7.i6.i1" to="tmp_58_cast" fromId="480" toId="92">
</dataflow>
<dataflow id="482" from="trunc_ln72_1" to="tmp_58_cast" fromId="91" toId="92">
</dataflow>
<dataflow id="484" from="StgValue_483" to="tmp_58_cast" fromId="483" toId="92">
</dataflow>
<dataflow id="485" from="tmp_57_cast" to="sub_ln72" fromId="90" toId="93">
</dataflow>
<dataflow id="486" from="tmp_58_cast" to="sub_ln72" fromId="92" toId="93">
</dataflow>
<dataflow id="487" from="wp_parameters_addr" to="wp_parameters_load" fromId="27" toId="94">
</dataflow>
<dataflow id="488" from="wp_parameters_addr" to="wp_parameters_load_13" fromId="27" toId="95">
</dataflow>
<dataflow id="489" from="sub_ln72" to="zext_ln72" fromId="93" toId="96">
</dataflow>
<dataflow id="490" from="wp_parameters" to="wp_parameters_addr_30" fromId="163" toId="97">
</dataflow>
<dataflow id="491" from="StgValue_168" to="wp_parameters_addr_30" fromId="168" toId="97">
</dataflow>
<dataflow id="492" from="zext_ln72" to="wp_parameters_addr_30" fromId="96" toId="97">
</dataflow>
<dataflow id="493" from="a_V" to="store_ln72" fromId="82" toId="98">
</dataflow>
<dataflow id="494" from="wp_parameters_addr_30" to="store_ln72" fromId="97" toId="98">
</dataflow>
<dataflow id="495" from="wp_parameters_addr" to="wp_parameters_load" fromId="27" toId="99">
</dataflow>
<dataflow id="496" from="wp_parameters_load" to="trunc_ln73" fromId="99" toId="100">
</dataflow>
<dataflow id="497" from="_ssdm_op_BitConcatenate.i7.i4.i3" to="tmp_59_cast" fromId="474" toId="101">
</dataflow>
<dataflow id="498" from="trunc_ln73" to="tmp_59_cast" fromId="100" toId="101">
</dataflow>
<dataflow id="499" from="StgValue_477" to="tmp_59_cast" fromId="477" toId="101">
</dataflow>
<dataflow id="500" from="wp_parameters_load" to="trunc_ln73_1" fromId="99" toId="102">
</dataflow>
<dataflow id="501" from="_ssdm_op_BitConcatenate.i7.i6.i1" to="tmp_60_cast" fromId="480" toId="103">
</dataflow>
<dataflow id="502" from="trunc_ln73_1" to="tmp_60_cast" fromId="102" toId="103">
</dataflow>
<dataflow id="503" from="StgValue_483" to="tmp_60_cast" fromId="483" toId="103">
</dataflow>
<dataflow id="504" from="tmp_59_cast" to="sub_ln73" fromId="101" toId="104">
</dataflow>
<dataflow id="505" from="tmp_60_cast" to="sub_ln73" fromId="103" toId="104">
</dataflow>
<dataflow id="506" from="wp_parameters_addr" to="wp_parameters_load_13" fromId="27" toId="105">
</dataflow>
<dataflow id="507" from="wp_parameters_load_13" to="trunc_ln75" fromId="105" toId="106">
</dataflow>
<dataflow id="508" from="_ssdm_op_BitConcatenate.i7.i4.i3" to="tmp_61_cast" fromId="474" toId="107">
</dataflow>
<dataflow id="509" from="trunc_ln75" to="tmp_61_cast" fromId="106" toId="107">
</dataflow>
<dataflow id="510" from="StgValue_477" to="tmp_61_cast" fromId="477" toId="107">
</dataflow>
<dataflow id="511" from="wp_parameters_load_13" to="trunc_ln75_1" fromId="105" toId="108">
</dataflow>
<dataflow id="512" from="_ssdm_op_BitConcatenate.i7.i6.i1" to="tmp_62_cast" fromId="480" toId="109">
</dataflow>
<dataflow id="513" from="trunc_ln75_1" to="tmp_62_cast" fromId="108" toId="109">
</dataflow>
<dataflow id="514" from="StgValue_483" to="tmp_62_cast" fromId="483" toId="109">
</dataflow>
<dataflow id="515" from="tmp_61_cast" to="sub_ln75" fromId="107" toId="110">
</dataflow>
<dataflow id="516" from="tmp_62_cast" to="sub_ln75" fromId="109" toId="110">
</dataflow>
<dataflow id="517" from="wp_parameters_addr" to="wp_parameters_load_14" fromId="27" toId="111">
</dataflow>
<dataflow id="518" from="sub_ln73" to="or_ln73" fromId="104" toId="112">
</dataflow>
<dataflow id="520" from="StgValue_519" to="or_ln73" fromId="519" toId="112">
</dataflow>
<dataflow id="521" from="or_ln73" to="zext_ln73" fromId="112" toId="113">
</dataflow>
<dataflow id="522" from="wp_parameters" to="wp_parameters_addr_31" fromId="163" toId="114">
</dataflow>
<dataflow id="523" from="StgValue_168" to="wp_parameters_addr_31" fromId="168" toId="114">
</dataflow>
<dataflow id="524" from="zext_ln73" to="wp_parameters_addr_31" fromId="113" toId="114">
</dataflow>
<dataflow id="525" from="sub_ln73" to="add_ln74" fromId="104" toId="115">
</dataflow>
<dataflow id="527" from="StgValue_526" to="add_ln74" fromId="526" toId="115">
</dataflow>
<dataflow id="528" from="add_ln74" to="zext_ln74" fromId="115" toId="116">
</dataflow>
<dataflow id="529" from="wp_parameters" to="wp_parameters_addr_32" fromId="163" toId="117">
</dataflow>
<dataflow id="530" from="StgValue_168" to="wp_parameters_addr_32" fromId="168" toId="117">
</dataflow>
<dataflow id="531" from="zext_ln74" to="wp_parameters_addr_32" fromId="116" toId="117">
</dataflow>
<dataflow id="532" from="b_V" to="store_ln73" fromId="83" toId="118">
</dataflow>
<dataflow id="533" from="wp_parameters_addr_31" to="store_ln73" fromId="114" toId="118">
</dataflow>
<dataflow id="534" from="c_V" to="store_ln74" fromId="84" toId="119">
</dataflow>
<dataflow id="535" from="wp_parameters_addr_32" to="store_ln74" fromId="117" toId="119">
</dataflow>
<dataflow id="536" from="wp_parameters_addr" to="wp_parameters_load_14" fromId="27" toId="120">
</dataflow>
<dataflow id="537" from="wp_parameters_load_14" to="trunc_ln77" fromId="120" toId="121">
</dataflow>
<dataflow id="538" from="_ssdm_op_BitConcatenate.i7.i4.i3" to="tmp_63_cast" fromId="474" toId="122">
</dataflow>
<dataflow id="539" from="trunc_ln77" to="tmp_63_cast" fromId="121" toId="122">
</dataflow>
<dataflow id="540" from="StgValue_477" to="tmp_63_cast" fromId="477" toId="122">
</dataflow>
<dataflow id="541" from="wp_parameters_load_14" to="trunc_ln77_1" fromId="120" toId="123">
</dataflow>
<dataflow id="542" from="_ssdm_op_BitConcatenate.i7.i6.i1" to="tmp_64_cast" fromId="480" toId="124">
</dataflow>
<dataflow id="543" from="trunc_ln77_1" to="tmp_64_cast" fromId="123" toId="124">
</dataflow>
<dataflow id="544" from="StgValue_483" to="tmp_64_cast" fromId="483" toId="124">
</dataflow>
<dataflow id="545" from="tmp_63_cast" to="sub_ln77" fromId="122" toId="125">
</dataflow>
<dataflow id="546" from="tmp_64_cast" to="sub_ln77" fromId="124" toId="125">
</dataflow>
<dataflow id="547" from="sub_ln77" to="add_ln77" fromId="125" toId="126">
</dataflow>
<dataflow id="549" from="StgValue_548" to="add_ln77" fromId="548" toId="126">
</dataflow>
<dataflow id="550" from="sub_ln75" to="add_ln75" fromId="110" toId="127">
</dataflow>
<dataflow id="552" from="StgValue_551" to="add_ln75" fromId="551" toId="127">
</dataflow>
<dataflow id="553" from="add_ln75" to="zext_ln75" fromId="127" toId="128">
</dataflow>
<dataflow id="554" from="wp_parameters" to="wp_parameters_addr_33" fromId="163" toId="129">
</dataflow>
<dataflow id="555" from="StgValue_168" to="wp_parameters_addr_33" fromId="168" toId="129">
</dataflow>
<dataflow id="556" from="zext_ln75" to="wp_parameters_addr_33" fromId="128" toId="129">
</dataflow>
<dataflow id="557" from="sub_ln75" to="add_ln76" fromId="110" toId="130">
</dataflow>
<dataflow id="559" from="StgValue_558" to="add_ln76" fromId="558" toId="130">
</dataflow>
<dataflow id="560" from="add_ln76" to="zext_ln76" fromId="130" toId="131">
</dataflow>
<dataflow id="561" from="wp_parameters" to="wp_parameters_addr_34" fromId="163" toId="132">
</dataflow>
<dataflow id="562" from="StgValue_168" to="wp_parameters_addr_34" fromId="168" toId="132">
</dataflow>
<dataflow id="563" from="zext_ln76" to="wp_parameters_addr_34" fromId="131" toId="132">
</dataflow>
<dataflow id="564" from="d_V" to="store_ln75" fromId="85" toId="133">
</dataflow>
<dataflow id="565" from="wp_parameters_addr_33" to="store_ln75" fromId="129" toId="133">
</dataflow>
<dataflow id="566" from="sext_ln43" to="store_ln76" fromId="36" toId="134">
</dataflow>
<dataflow id="567" from="wp_parameters_addr_34" to="store_ln76" fromId="132" toId="134">
</dataflow>
<dataflow id="568" from="add_ln77" to="zext_ln77" fromId="126" toId="135">
</dataflow>
<dataflow id="569" from="wp_parameters" to="wp_parameters_addr_35" fromId="163" toId="136">
</dataflow>
<dataflow id="570" from="StgValue_168" to="wp_parameters_addr_35" fromId="168" toId="136">
</dataflow>
<dataflow id="571" from="zext_ln77" to="wp_parameters_addr_35" fromId="135" toId="136">
</dataflow>
<dataflow id="572" from="sext_ln46" to="store_ln77" fromId="34" toId="137">
</dataflow>
<dataflow id="573" from="wp_parameters_addr_35" to="store_ln77" fromId="136" toId="137">
</dataflow>
<dataflow id="574" from="wp_parameters_load_14" to="add_ln691" fromId="120" toId="138">
</dataflow>
<dataflow id="575" from="StgValue_165" to="add_ln691" fromId="165" toId="138">
</dataflow>
<dataflow id="576" from="add_ln691" to="store_ln691" fromId="138" toId="139">
</dataflow>
<dataflow id="577" from="wp_parameters_addr" to="store_ln691" fromId="27" toId="139">
</dataflow>
<dataflow id="578" from="add_ln691" to="store_ln80" fromId="138" toId="140">
</dataflow>
<dataflow id="579" from="empty" to="store_ln80" fromId="17" toId="140">
</dataflow>
<dataflow id="580" from="icmp_ln59" to="StgValue_4" fromId="47" toId="4">
</dataflow>
<dataflow id="581" from="icmp_ln70" to="StgValue_12" fromId="87" toId="12">
</dataflow>
<dataflow id="582" from="icmp_ln70" to="StgValue_16" fromId="87" toId="16">
</dataflow>
</dataflows>


</stg>
